homework/homework03/adder/add32.v
`include "add16.v"
`define byname 0
// `define byport 0

module add32 (
    a, b, cin, sum, cout
);
    

input [31:0] a, b;
input cin;
output [31:0] sum;
output cout;

wire [15:0] ah, al, bh, bl, sh, sl;
wire cout_l;

assign sum = {sh, sl};

`ifdef byport
add16 u_l(
    .a(al),
    .b(bl),
    .cin(cin),
    .sum(sl),
    .cout(cout_l)
);

add16 u_h(
    .a(ah),
    .b(bh),
    .cin(cout_l),
    .sum(sh),
    .cout(cout)
);
`endif


`ifdef byname
add16 u_l(
    al,
    bl,
    cin,
    sl,
    cout_l
);

add16 u_h(
    ah,
    bh,
    cout_l,
    sh,
    cout
);
`endif


endmodule

homework/homework03/adder/add16.v
`define addbit 16
`define Module_16 0


module add16 (
    a, b, cin, sum, cout
);

input [15:0] a, b;
input cin;
output [15:0] sum;
output cout;

assign {cout, sum} = a + b + cin;


initial begin
    $display(`addbit);
end
    
endmodule

homework/homework03/task1-3-adder/test.v
// `include "add16.v"
`include "add32.v"

module test (
);

reg [`addbit-1:0] a, b;
reg cin;
wire [`addbit:0] ans;

`ifdef Module_32 

add32 u_add(
    .a(a),
    .b(b),
    .cin(cin),
    .cout(ans[`addbit]),
    .sum(ans[`addbit - 1 : 0])
);

`else


add16 u_add(
    .a(a),
    .b(b),
    .cin(cin),
    .cout(ans[`addbit]),
    .sum(ans[`addbit - 1 : 0])
);

`endif 

reg [`addbit-1:0] a_test[99:0];
reg [`addbit-1:0] b_test[99:0];
reg cin_test [99:0];
reg [`addbit:0] ans_test[99:0];

integer i;

initial begin
    $dumpfile("test.vcd");
    $dumpvars;    
    $readmemb("add1.in", a_test);
    $readmemb("add2.in", b_test);
    $readmemb("cin.in", cin_test);
    $readmemb("ans.out", ans_test);

    for (i = 0; i < 100; i = i + 1) begin
        #1;
        a = a_test[i];
        b = b_test[i];
        cin = cin_test[i];
        #1;
        if (ans !== ans_test[i]) begin
            $display("test failed at %d! in1: %x in2: %x, cin: %x, out: %x, should: %x", i, a, b, cin, ans, ans_test[i]);
            $finish;
        end
    end
    $display("add %d test passed", `addbit);
    $finish;
end

endmodule

homework/homework03/adder/test.vcd
$date
	Fri Sep 25 16:14:17 2020
$end
$version
	Icarus Verilog
$end
$timescale
	1s
$end
$scope module test $end
$var wire 17 ! ans [16:0] $end
$var reg 16 " a [15:0] $end
$var reg 16 # b [15:0] $end
$var reg 1 $ cin $end
$var integer 32 % i [31:0] $end
$scope module u_add $end
$var wire 16 & a [15:0] $end
$var wire 16 ' b [15:0] $end
$var wire 1 $ cin $end
$var wire 16 ( sum [15:0] $end
$var wire 1 ) cout $end
$upscope $end
$upscope $end
$enddefinitions $end
#0
$dumpvars
x)
bx (
bx '
bx &
b0 %
x$
bx #
bx "
bx !
$end
#1
b1001100100100000 (
b1001100100100000 !
0)
1$
b10011000011100 #
b10011000011100 '
b111001100000011 "
b111001100000011 &
#2
b1 %
#3
1)
b10010110111100101 !
b10110111100101 (
0$
b1100011101110000 #
b1100011101110000 '
b110011001110101 "
b110011001110101 &
#4
b10 %
#5
0)
b1001000001110011 !
b1001000001110011 (
b10011110000111 #
b10011110000111 '
b110100011101100 "
b110100011101100 &
#6
b11 %
#7
b1011110001111001 !
b1011110001111001 (
b1011100001110 #
b1011100001110 '
b1010010101101011 "
b1010010101101011 &
#8
b100 %
#9
1)
b11001111000101110 !
b1001111000101110 (
1$
b1011011111110111 #
b1011011111110111 '
b1110011000110110 "
b1110011000110110 &
#10
b101 %
#11
b1011111011111010 (
b1011111011111010 !
0)
b1011001001101100 #
b1011001001101100 '
b110010001101 "
b110010001101 &
#12
b110 %
#13
b1111001000101010 !
b1111001000101010 (
0$
b1010101101011010 #
b1010101101011010 '
b100011011010000 "
b100011011010000 &
#14
b111 %
#15
b1010111001101110 !
b1010111001101110 (
1$
b110100110101101 #
b110100110101101 '
b100010011000000 "
b100010011000000 &
#16
b1000 %
#17
1)
b10101110101101010 !
b101110101101010 (
b1111011101001111 #
b1111011101001111 '
b110011000011010 "
b110011000011010 &
#18
b1001 %
#19
0)
b11101100110111 !
b11101100110111 (
b1101111011101 #
b1101111011101 '
b1111101011001 "
b1111101011001 &
#20
b1010 %
#21
b1001011001000 !
b1001011001000 (
b1000110001011 #
b1000110001011 '
b100111100 "
b100111100 &
#22
b1011 %
#23
1)
b11000110010111000 !
b1000110010111000 (
b1101010100010110 #
b1101010100010110 '
b1011011110100001 "
b1011011110100001 &
#24
b1100 %
#25
b1111011101010000 (
b1111011101010000 !
0)
0$
b1110000100000010 #
b1110000100000010 '
b1011001001110 "
b1011001001110 &
#26
b1101 %
#27
b1010111101111100 !
b1010111101111100 (
1$
b1000001110 #
b1000001110 '
b1010110101101101 "
b1010110101101101 &
#28
b1110 %
#29
1)
b10010100011000101 !
b10100011000101 (
0$
b1011010000101110 #
b1011010000101110 '
b111010010010111 "
b111010010010111 &
#30
b1111 %
#31
b11110101010010110 !
b1110101010010110 (
1$
b1111100010100111 #
b1111100010100111 '
b1111000111101110 "
b1111000111101110 &
#32
b10000 %
#33
0)
b100100011101001 !
b100100011101001 (
b110110001011 #
b110110001011 '
b11101101011101 "
b11101101011101 &
#34
b10001 %
#35
b1000011100001010 !
b1000011100001010 (
0$
b11111100000000 #
b11111100000000 '
b100100000001010 "
b100100000001010 &
#36
b10010 %
#37
b11000101000110 (
b10011000101000110 !
1)
1$
b110110100101010 #
b110110100101010 '
b1100010000011011 "
b1100010000011011 &
#38
b10011 %
#39
b11010111011010000 !
b1010111011010000 (
b1100110010110010 #
b1100110010110010 '
b1110001000011101 "
b1110001000011101 &
#40
b10100 %
#41
b10100001101010000 !
b100001101010000 (
b1101001010011010 #
b1101001010011010 '
b111000010110101 "
b111000010110101 &
#42
b10101 %
#43
b11000011101111010 !
b1000011101111010 (
0$
b1001101001111101 #
b1001101001111101 '
b1110110011111101 "
b1110110011111101 &
#44
b10110 %
#45
b110001101010000 (
b110001101010000 !
0)
1$
b1101110000100 #
b1101110000100 '
b100011111001011 "
b100011111001011 &
#46
b10111 %
#47
1)
b10011100011011011 !
b11100011011011 (
0$
b1100100101101101 #
b1100100101101101 '
b110111101101110 "
b110111101101110 &
#48
b11000 %
#49
b10111111100110101 !
b111111100110101 (
b1010010111011111 #
b1010010111011111 '
b1101100101010110 "
b1101100101010110 &
#50
b11001 %
#51
b10101110000011101 !
b101110000011101 (
b1011100110111000 #
b1011100110111000 '
b1010001001100101 "
b1010001001100101 &
#52
b11010 %
#53
b101101100010101 (
b101101100010101 !
0)
1$
b11110010100000 #
b11110010100000 '
b1111001110100 "
b1111001110100 &
#54
b11011 %
#55
b1110000011011000 (
b11110000011011000 !
1)
b1111010001100101 #
b1111010001100101 '
b1110110001110010 "
b1110110001110010 &
#56
b11100 %
#57
b10011101111001001 !
b11101111001001 (
b1100001100000011 #
b1100001100000011 '
b111100011000101 "
b111100011000101 &
#58
b11101 %
#59
b11000001111110010 !
b1000001111110010 (
b1000100110000011 #
b1000100110000011 '
b1111101001101110 "
b1111101001101110 &
#60
b11110 %
#61
b1111100110001010 (
b1111100110001010 !
0)
0$
b1100010110110101 #
b1100010110110101 '
b11001111010101 "
b11001111010101 &
#62
b11111 %
#63
b1001001110010111 (
b11001001110010111 !
1)
1$
b1111111111111100 #
b1111111111111100 '
b1001001110011010 "
b1001001110011010 &
#64
b100000 %
#65
b10011001011011011 !
b11001011011011 (
b111011001101111 #
b111011001101111 '
b1011110001101011 "
b1011110001101011 &
#66
b100001 %
#67
b10001101110011100 !
b1101110011100 (
0$
b101001011111100 #
b101001011111100 '
b1100100010100000 "
b1100100010100000 &
#68
b100010 %
#69
b111111010001100 (
b111111010001100 !
0)
1$
b100001010011000 #
b100001010011000 '
b11101111110011 "
b11101111110011 &
#70
b100011 %
#71
1)
b10011001000010100 !
b11001000010100 (
0$
b1000011010011101 #
b1000011010011101 '
b1010101101110111 "
b1010101101110111 &
#72
b100100 %
#73
b111010100010001 (
b111010100010001 !
0)
b101010010010111 #
b101010010010111 '
b10000001111010 "
b10000001111010 &
#74
b100101 %
#75
b1011101111010001 (
b11011101111010001 !
1)
1$
b1111011110110011 #
b1111011110110011 '
b1100010000011101 "
b1100010000011101 &
#76
b100110 %
#77
0)
b1111001100010111 !
b1111001100010111 (
0$
b10011111000100 #
b10011111000100 '
b1100101101010011 "
b1100101101010011 &
#78
b100111 %
#79
b1011010001010011 !
b1011010001010011 (
1$
b1000001101000011 #
b1000001101000011 '
b11000100001111 "
b11000100001111 &
#80
b101000 %
#81
b100001101011000 (
b10100001101011000 !
1)
0$
b110001001111101 #
b110001001111101 '
b1110000011011011 "
b1110000011011011 &
#82
b101001 %
#83
b101100000100 (
b101100000100 !
0)
1$
b10100000100 #
b10100000100 '
b10111111111 "
b10111111111 &
#84
b101010 %
#85
b1011000100001111 !
b1011000100001111 (
b11110010011001 #
b11110010011001 '
b111010001110101 "
b111010001110101 &
#86
b101011 %
#87
b1101011111100001 (
b11101011111100001 !
1)
b1110000101101111 #
b1110000101101111 '
b1111011001110001 "
b1111011001110001 &
#88
b101100 %
#89
b11001111011001110 !
b1001111011001110 (
b1010001111111111 #
b1010001111111111 '
b1111101011001110 "
b1111101011001110 &
#90
b101101 %
#91
b11010100111000010 !
b1010100111000010 (
0$
b1011000100111011 #
b1011000100111011 '
b1111100010000111 "
b1111100010000111 &
#92
b101110 %
#93
b1100010001100000 (
b1100010001100000 !
0)
1$
b1011010110001011 #
b1011010110001011 '
b111011010100 "
b111011010100 &
#94
b101111 %
#95
b1010100110011 (
b10001010100110011 !
1)
0$
b111101000000011 #
b111101000000011 '
b1001101100110000 "
b1001101100110000 &
#96
b110000 %
#97
b1110111010000001 (
b1110111010000001 !
0)
b1010000010011010 #
b1010000010011010 '
b100110111100111 "
b100110111100111 &
#98
b110001 %
#99
b100011101110100 (
b10100011101110100 !
1)
b1010010110110110 #
b1010010110110110 '
b1010000110111110 "
b1010000110111110 &
#100
b110010 %
#101
0)
b1111111100111010 !
b1111111100111010 (
1$
b1001111111110110 #
b1001111111110110 '
b101111101000011 "
b101111101000011 &
#102
b110011 %
#103
b1011101010101011 !
b1011101010101011 (
b11111101111001 #
b11111101111001 '
b111101100110001 "
b111101100110001 &
#104
b110100 %
#105
b1110101100110010 !
b1110101100110010 (
0$
b1000100101110 #
b1000100101110 '
b1101101000000100 "
b1101101000000100 &
#106
b110101 %
#107
b111010101011111 (
b10111010101011111 !
1)
1$
b1000010111001110 #
b1000010111001110 '
b1110111110010000 "
b1110111110010000 &
#108
b110110 %
#109
0)
b1111011011011101 !
b1111011011011101 (
b110001011000110 #
b110001011000110 '
b1001010000010110 "
b1001010000010110 &
#110
b110111 %
#111
b1001010110001101 !
b1001010110001101 (
0$
b101010010111011 #
b101010010111011 '
b100000011010010 "
b100000011010010 &
#112
b111000 %
#113
b1111001000101001 !
b1111001000101001 (
1$
b110101001001110 #
b110101001001110 '
b1000011111011010 "
b1000011111011010 &
#114
b111001 %
#115
b1100100111010100 (
b11100100111010100 !
1)
0$
b1101101111111111 #
b1101101111111111 '
b1110110111010101 "
b1110110111010101 &
#116
b111010 %
#117
0)
b1010011001111111 !
b1010011001111111 (
1$
b11000010001101 #
b11000010001101 '
b111010111110001 "
b111010111110001 &
#118
b111011 %
#119
b1000000111110001 (
b11000000111110001 !
1)
0$
b1000011100110100 #
b1000011100110100 '
b1111101010111101 "
b1111101010111101 &
#120
b111100 %
#121
b1001000100110111 (
b1001000100110111 !
0)
1$
b100001110011101 #
b100001110011101 '
b100110110011001 "
b100110110011001 &
#122
b111101 %
#123
b1110101110111001 !
b1110101110111001 (
b11111101100000 #
b11111101100000 '
b1010110001011000 "
b1010110001011000 &
#124
b111110 %
#125
b1000111110100100 !
b1000111110100100 (
b111011010100110 #
b111011010100110 '
b1100011111101 "
b1100011111101 &
#126
b111111 %
#127
b1110010101010111 !
b1110010101010111 (
0$
b10011101010100 #
b10011101010100 '
b1011111000000011 "
b1011111000000011 &
#128
b1000000 %
#129
1)
b10110011010001101 !
b110011010001101 (
b1101001100111101 #
b1101001100111101 '
b1001001101010000 "
b1001001101010000 &
#130
b1000001 %
#131
b1000100100011100 (
b1000100100011100 !
0)
1$
b110010011001100 #
b110010011001100 '
b10010001001111 "
b10010001001111 &
#132
b1000010 %
#133
b1100010000100010 !
b1100010000100010 (
0$
b10111101001101 #
b10111101001101 '
b1001010011010101 "
b1001010011010101 &
#134
b1000011 %
#135
b1101101011111111 !
b1101101011111111 (
b11101100100000 #
b11101100100000 '
b1001111111011111 "
b1001111111011111 &
#136
b1000100 %
#137
b1101001010101011 (
b11101001010101011 !
1)
1$
b1111000000000000 #
b1111000000000000 '
b1110001010101010 "
b1110001010101010 &
#138
b1000101 %
#139
0)
b1111011101111110 !
b1111011101111110 (
0$
b111010001111011 #
b111010001111011 '
b1000001100000011 "
b1000001100000011 &
#140
b1000110 %
#141
b1001011000101110 !
b1001011000101110 (
b1001001010001101 #
b1001001010001101 '
b1110100001 "
b1110100001 &
#142
b1000111 %
#143
b1011001101110011 !
b1011001101110011 (
1$
b101011110100100 #
b101011110100100 '
b101101111001110 "
b101101111001110 &
#144
b1001000 %
#145
b1001110011011110 (
b11001110011011110 !
1)
0$
b1011100111101010 #
b1011100111101010 '
b1110001011110100 "
b1110001011110100 &
#146
b1001001 %
#147
b10000011111010000 !
b11111010000 (
1$
b1001101000001101 #
b1001101000001101 '
b110110111000010 "
b110110111000010 &
#148
b1001010 %
#149
b10100100100110010 !
b100100100110010 (
0$
b110001100110101 #
b110001100110101 '
b1110010111111101 "
b1110010111111101 &
#150
b1001011 %
#151
b10000001001111000 !
b1001111000 (
1$
b110010010001001 #
b110010010001001 '
b1001110111101110 "
b1001110111101110 &
#152
b1001100 %
#153
b10001101111101001 !
b1101111101001 (
b1011100100001111 #
b1011100100001111 '
b110001011011001 "
b110001011011001 &
#154
b1001101 %
#155
b11111001110100 (
b11111001110100 !
0)
0$
b1111010000001 #
b1111010000001 '
b1111111110011 "
b1111111110011 &
#156
b1001110 %
#157
1)
b10100110101110010 !
b100110101110010 (
1$
b1100001101010001 #
b1100001101010001 '
b1000101000100000 "
b1000101000100000 &
#158
b1001111 %
#159
0)
b1110011111111101 !
b1110011111111101 (
b11000100011010 #
b11000100011010 '
b1011011011100010 "
b1011011011100010 &
#160
b1010000 %
#161
b111110111001011 (
b10111110111001011 !
1)
b1001111011010100 #
b1001111011010100 '
b1101111011110110 "
b1101111011110110 &
#162
b1010001 %
#163
b1000101100100011 (
b1000101100100011 !
0)
b101111011111000 #
b101111011111000 '
b10110000101010 "
b10110000101010 &
#164
b1010010 %
#165
1)
b11001010100110001 !
b1001010100110001 (
0$
b1111110110111110 #
b1111110110111110 '
b1001011101110011 "
b1001011101110011 &
#166
b1010011 %
#167
b10000010101111100 !
b10101111100 (
b1111110100100000 #
b1111110100100000 '
b100001011100 "
b100001011100 &
#168
b1010100 %
#169
b10101111010000001 !
b101111010000001 (
b111001010011101 #
b111001010011101 '
b1110101111100100 "
b1110101111100100 &
#170
b1010101 %
#171
b1111110111001100 (
b1111110111001100 !
0)
b1001101101101100 #
b1001101101101100 '
b110001001100000 "
b110001001100000 &
#172
b1010110 %
#173
b1101011001100110 (
b11101011001100110 !
1)
b1110100000010101 #
b1110100000010101 '
b1110111001010001 "
b1110111001010001 &
#174
b1010111 %
#175
0)
b1111010011111100 !
b1111010011111100 (
1$
b11001101101111 #
b11001101101111 '
b1100000110001100 "
b1100000110001100 &
#176
b1011000 %
#177
b1011011111110000 (
b11011011111110000 !
1)
b1110010101101111 #
b1110010101101111 '
b1101001010000000 "
b1101001010000000 &
#178
b1011001 %
#179
b101111000011010 (
b101111000011010 !
0)
b100111001101101 #
b100111001101101 '
b111110101100 "
b111110101100 &
#180
b1011010 %
#181
b101011010010011 !
b101011010010011 (
b110001111110 #
b110001111110 '
b100101000010100 "
b100101000010100 &
#182
b1011011 %
#183
1)
b10000111111001100 !
b111111001100 (
b1100011000110101 #
b1100011000110101 '
b100100110010110 "
b100100110010110 &
#184
b1011100 %
#185
b1101000000011 (
b1101000000011 !
0)
0$
b11111010101 #
b11111010101 '
b1001000101110 "
b1001000101110 &
#186
b1011101 %
#187
1)
b11010101001010010 !
b1010101001010010 (
1$
b1110010110101111 #
b1110010110101111 '
b1100010010100010 "
b1100010010100010 &
#188
b1011110 %
#189
b11100101100001110 !
b1100101100001110 (
0$
b1111110110111101 #
b1111110110111101 '
b1100110101010001 "
b1100110101010001 &
#190
b1011111 %
#191
b10101000110001110 !
b101000110001110 (
1$
b1100101010001010 #
b1100101010001010 '
b1000011100000011 "
b1000011100000011 &
#192
b1100000 %
#193
0)
b1100011101011110 !
b1100011101011110 (
b11111100000010 #
b11111100000010 '
b1000100001011011 "
b1000100001011011 &
#194
b1100001 %
#195
1)
b10101111000110010 !
b101111000110010 (
0$
b1001111111101111 #
b1001111111101111 '
b1011111001000011 "
b1011111001000011 &
#196
b1100010 %
#197
b1111011111000001 (
b1111011111000001 !
0)
b1011100010010111 #
b1011100010010111 '
b11111100101010 "
b11111100101010 &
#198
b1100011 %
#199
b111011011100001 (
b10111011011100001 !
1)
1$
b1111000110011111 #
b1111000110011111 '
b1000010101000001 "
b1000010101000001 &
#200
b1100100 %
