homework/homework03/7458/7458v1.v
`define Module_v1 0

module _7458v1 (
    p1a, 
    p1b,
    p1c,
    p1d,
    p1e,
    p1f,
    p1y,
    
    p2a, 
    p2b,
    p2c,
    p2d,
    p2y
);

input p1a, p1b, p1c, p1d, p1e, p1f;
input p2a, p2b, p2c, p2d;
output p1y;
output p2y;

wire and1, and2, and3, and4;

assign and1 = p1a & p1b & p1c;
assign and2 = p1d & p1e & p1f;
assign and3 = p2a & p2b; 
assign and4 = p2c & p2d;

assign p1y = and1 | and2;
assign p2y = and3 | and4;
    
endmodule

homework/homework03/7458/7458v2.v
`define Module_v2 0

module _7458v2 (
    p1a, 
    p1b,
    p1c,
    p1d,
    p1e,
    p1f,
    p1y,
    
    p2a, 
    p2b,
    p2c,
    p2d,
    p2y
);

input p1a, p1b, p1c, p1d, p1e, p1f;
input p2a, p2b, p2c, p2d;
output p1y;
output p2y;

wire and1, and2, and3, and4;

// assign and1 = p1a & p1b & p1c;
and u_and1(and1, p1a, p1b, p1c);
// assign and2 = p1d & p1e & p1f;
and u_and2(and2, p1d, p1e, p1f);
// assign and3 = p2a & p2b; 
and u_and3(and3, p2a, p2b);
// assign and4 = p2c & p2d;
and u_and4(and4, p2c, p2d);

// assign p1y = and1 | and2;
or u_or1(p1y, and1, and2);
// assign p2y = and3 | and4;
or u_or2(p2y, and3, and4);
    
endmodule

homework/homework03/task-1-1-7458/test_7458.v
`include "7458v1.v"
// `include "7458v2.v"

module test (

);

reg [5:0] p1;
reg [3:0] p2;

wire [1:0] py;



`ifdef Module_v1
_7458v1 u_7458(
    .p1a(p1[0]),
    .p1b(p1[1]),
    .p1c(p1[2]),
    .p1d(p1[3]),
    .p1e(p1[4]),
    .p1f(p1[5]),

    .p2a(p2[0]),
    .p2b(p2[1]),
    .p2c(p2[2]),
    .p2d(p2[3]),

    .p1y(py[0]),
    .p2y(py[1])
);
`else 
_7458v2 u_7458(
    .p1a(p1[0]),
    .p1b(p1[1]),
    .p1c(p1[2]),
    .p1d(p1[3]),
    .p1e(p1[4]),
    .p1f(p1[5]),

    .p2a(p2[0]),
    .p2b(p2[1]),
    .p2c(p2[2]),
    .p2d(p2[3]),

    .p1y(py[0]),
    .p2y(py[1])
);
`endif  

reg [5:0] p1_test [99:0];
reg [3:0] p2_test [99:0];
reg [1:0] ans_test [99:0];

integer i;

initial begin
    $dumpfile("test_7458.vcd");
    $dumpvars;
    // p1 = 6'b101111;
    // p2 = 4'b1101;
    $readmemb("p1.in", p1_test);
    $readmemb("p2.in", p2_test);
    $readmemb("p.out", ans_test);
    for (i = 0; i < 100; i = i + 1) begin
        p1 = p1_test[i];
        p2 = p2_test[i];
        #1;
        if (py !== ans_test[i]) begin
            $display("test failed at %d! in1: %x in2: %x out: %x, should: %x", i, p1, p2, py, ans_test[i]);
            $finish;
        end
    end
    $display("test passed");
    #1 $finish;
end



endmodule

homework/homework03/task-1-1-7458/test_7458.vcd
$date
	Mon Sep 28 21:46:06 2020
$end
$version
	Icarus Verilog
$end
$timescale
	1s
$end
$scope module test $end
$var wire 2 ! py [1:0] $end
$var reg 6 " p1 [5:0] $end
$var reg 4 # p2 [3:0] $end
$var integer 32 $ i [31:0] $end
$scope module u_7458 $end
$var wire 1 % and1 $end
$var wire 1 & and2 $end
$var wire 1 ' and3 $end
$var wire 1 ( and4 $end
$var wire 1 ) p1a $end
$var wire 1 * p1b $end
$var wire 1 + p1c $end
$var wire 1 , p1d $end
$var wire 1 - p1e $end
$var wire 1 . p1f $end
$var wire 1 / p1y $end
$var wire 1 0 p2a $end
$var wire 1 1 p2b $end
$var wire 1 2 p2c $end
$var wire 1 3 p2d $end
$var wire 1 4 p2y $end
$upscope $end
$upscope $end
$enddefinitions $end
#0
$dumpvars
x4
x3
x2
x1
x0
x/
x.
x-
x,
x+
x*
x)
x(
x'
x&
x%
b0 $
bx #
bx "
bx !
$end
#1
b1 $
#2
b10 $
#3
b11 $
#4
b100 $
#5
b101 $
#6
b110 $
#7
b111 $
#8
b1000 $
#9
b1001 $
#10
b1010 $
#11
b1011 $
#12
b1100 $
#13
b1101 $
#14
b1110 $
#15
b1111 $
#16
b10000 $
#17
b10001 $
#18
b10010 $
#19
b10011 $
#20
b10100 $
#21
b10101 $
#22
b10110 $
#23
b10111 $
#24
b11000 $
#25
b11001 $
#26
b11010 $
#27
b11011 $
#28
b11100 $
#29
b11101 $
#30
b11110 $
#31
b11111 $
#32
b100000 $
#33
b100001 $
#34
b100010 $
#35
b100011 $
#36
b100100 $
#37
b100101 $
#38
b100110 $
#39
b100111 $
#40
b101000 $
#41
b101001 $
#42
b101010 $
#43
b101011 $
#44
b101100 $
#45
b101101 $
#46
b101110 $
#47
b101111 $
#48
b110000 $
#49
b110001 $
#50
b110010 $
#51
b110011 $
#52
b110100 $
#53
b110101 $
#54
b110110 $
#55
b110111 $
#56
b111000 $
#57
b111001 $
#58
b111010 $
#59
b111011 $
#60
b111100 $
#61
b111101 $
#62
b111110 $
#63
b111111 $
#64
b1000000 $
#65
b1000001 $
#66
b1000010 $
#67
b1000011 $
#68
b1000100 $
#69
b1000101 $
#70
b1000110 $
#71
b1000111 $
#72
b1001000 $
#73
b1001001 $
#74
b1001010 $
#75
b1001011 $
#76
b1001100 $
#77
b1001101 $
#78
b1001110 $
#79
b1001111 $
#80
b1010000 $
#81
b1010001 $
#82
b1010010 $
#83
b1010011 $
#84
b1010100 $
#85
b1010101 $
#86
b1010110 $
#87
b1010111 $
#88
b1011000 $
#89
b1011001 $
#90
b1011010 $
#91
b1011011 $
#92
b1011100 $
#93
b1011101 $
#94
b1011110 $
#95
b1011111 $
#96
b1100000 $
#97
b1100001 $
#98
b1100010 $
#99
b1100011 $
#100
b1100100 $
