homework/homework03/7458/7458v1.v
`define Module_v1 0

module _7458v1 (
    p1a, 
    p1b,
    p1c,
    p1d,
    p1e,
    p1f,
    p1y,
    
    p2a, 
    p2b,
    p2c,
    p2d,
    p2y
);

input p1a, p1b, p1c, p1d, p1e, p1f;
input p2a, p2b, p2c, p2d;
output p1y;
output p2y;

wire and1, and2, and3, and4;

assign and1 = p1a & p1b & p1c;
assign and2 = p1d & p1e & p1f;
assign and3 = p2a & p2b; 
assign and4 = p2c & p2d;

assign p1y = and1 | and2;
assign p2y = and3 | and4;
    
endmodule

homework/homework03/7458/7458v2.v
`define Module_v2 0

module _7458v2 (
    p1a, 
    p1b,
    p1c,
    p1d,
    p1e,
    p1f,
    p1y,
    
    p2a, 
    p2b,
    p2c,
    p2d,
    p2y
);

input p1a, p1b, p1c, p1d, p1e, p1f;
input p2a, p2b, p2c, p2d;
output p1y;
output p2y;

wire and1, and2, and3, and4;

// assign and1 = p1a & p1b & p1c;
and u_and1(and1, p1a, p1b, p1c);
// assign and2 = p1d & p1e & p1f;
and u_and2(and2, p1d, p1e, p1f);
// assign and3 = p2a & p2b; 
and u_and3(and3, p2a, p2b);
// assign and4 = p2c & p2d;
and u_and4(and4, p2c, p2d);

// assign p1y = and1 | and2;
or u_or1(p1y, and1, and2);
// assign p2y = and3 | and4;
or u_or2(p2y, and3, and4);
    
endmodule

homework/homework03/task-1-1-7458/test_7458.v
`include "7458v1.v"
// `include "7458v2.v"

module test (

);

reg [5:0] p1;
reg [3:0] p2;

wire [1:0] py;



`ifdef Module_v1
_7458v1 u_7458(
    .p1a(p1[0]),
    .p1b(p1[1]),
    .p1c(p1[2]),
    .p1d(p1[3]),
    .p1e(p1[4]),
    .p1f(p1[5]),

    .p2a(p2[0]),
    .p2b(p2[1]),
    .p2c(p2[2]),
    .p2d(p2[3]),

    .p1y(py[0]),
    .p2y(py[1])
);
`else 
_7458v2 u_7458(
    .p1a(p1[0]),
    .p1b(p1[1]),
    .p1c(p1[2]),
    .p1d(p1[3]),
    .p1e(p1[4]),
    .p1f(p1[5]),

    .p2a(p2[0]),
    .p2b(p2[1]),
    .p2c(p2[2]),
    .p2d(p2[3]),

    .p1y(py[0]),
    .p2y(py[1])
);
`endif  

reg [5:0] p1_test [99:0];
reg [3:0] p2_test [99:0];
reg [1:0] ans_test [99:0];

integer i;

initial begin
    $dumpfile("test_7458.vcd");
    $dumpvars;
    // p1 = 6'b101111;
    // p2 = 4'b1101;
    $readmemb("p1.in", p1_test);
    $readmemb("p2.in", p2_test);
    $readmemb("p.out", ans_test);
    for (i = 0; i < 100; i = i + 1) begin
        p1 = p1_test[i];
        p2 = p2_test[i];
        #1;
        if (py !== ans_test[i]) begin
            $display("test failed at %d! in1: %x in2: %x out: %x, should: %x", i, p1, p2, py, ans_test[i]);
            $finish;
        end
    end
    $display("test passed");
    #1 $finish;
end



endmodule

homework/homework03/task-1-1-7458/test_7458.vcd
$date
	Tue Sep 29 08:28:41 2020
$end
$version
	Icarus Verilog
$end
$timescale
	1s
$end
$scope module test $end
$var wire 2 ! py [1:0] $end
$var reg 6 " p1 [5:0] $end
$var reg 4 # p2 [3:0] $end
$var integer 32 $ i [31:0] $end
$scope module u_7458 $end
$var wire 1 % and1 $end
$var wire 1 & and2 $end
$var wire 1 ' and3 $end
$var wire 1 ( and4 $end
$var wire 1 ) p1a $end
$var wire 1 * p1b $end
$var wire 1 + p1c $end
$var wire 1 , p1d $end
$var wire 1 - p1e $end
$var wire 1 . p1f $end
$var wire 1 / p1y $end
$var wire 1 0 p2a $end
$var wire 1 1 p2b $end
$var wire 1 2 p2c $end
$var wire 1 3 p2d $end
$var wire 1 4 p2y $end
$upscope $end
$upscope $end
$enddefinitions $end
#0
$dumpvars
04
03
02
01
10
0/
1.
1-
0,
1+
0*
1)
0(
0'
0&
0%
b0 $
b1 #
b110101 "
b0 !
$end
#1
00
11
1*
0+
1,
0-
0.
b10 #
b1011 "
b1 $
#2
b10 !
14
1(
01
12
13
0*
1.
b1100 #
b101001 "
b10 $
#3
1'
0(
10
11
02
0)
1*
1+
b1011 #
b101110 "
b11 $
#4
03
0+
0,
0.
b11 #
b10 "
b100 $
#5
0'
1(
00
01
12
13
0*
1,
1-
b1100 #
b11000 "
b101 $
#6
04
b0 !
0/
0(
0&
02
03
0,
1.
b0 #
b110000 "
b110 $
#7
11
1*
0-
0.
b10 #
b10 "
b111 $
#8
1/
b11 !
14
1&
1'
10
12
0*
1+
1,
1-
1.
b111 #
b111100 "
b1000 $
#9
b10 !
0/
0&
02
0-
0.
b11 #
b1100 "
b1001 $
#10
0'
1(
00
01
12
13
0+
1-
b1100 #
b11000 "
b1010 $
#11
1'
0(
10
11
03
1*
1+
0,
b111 #
b10110 "
b1011 $
#12
b0 !
04
0'
01
02
1)
0*
0+
1,
b1 #
b11001 "
b1100 $
#13
14
1%
b11 !
1/
1'
0&
11
12
1*
1+
0-
1.
b111 #
b101111 "
b1101 $
#14
04
b0 !
0/
0'
0%
00
02
0)
0+
0,
1-
b10 #
b110010 "
b1110 $
#15
b10 !
14
1(
10
01
12
13
1+
0.
b1101 #
b10110 "
b1111 $
#16
1/
b1 !
04
1%
0(
02
1)
0-
b1001 #
b111 "
b10000 $
#17
14
b10 !
0/
1'
0%
11
12
03
0)
0+
1-
1.
b111 #
b110010 "
b10001 $
#18
b0 !
04
0'
01
02
1)
0*
1,
0.
b1 #
b11001 "
b10010 $
#19
00
13
1*
b1000 #
b11011 "
b10011 $
#20
14
b11 !
1/
1'
1%
10
11
03
1+
0-
b11 #
b1111 "
b10100 $
#21
b10 !
0/
0%
12
0*
0+
1-
b111 #
b11001 "
b10101 $
#22
b0 !
04
0'
01
02
0)
1+
0-
b1 #
b1100 "
b10110 $
#23
00
11
12
1)
1*
0+
0,
b110 #
b11 "
b10111 $
#24
01
0*
1-
b100 #
b10001 "
b11000 $
#25
11
1*
1,
b110 #
b11011 "
b11001 $
#26
b0 !
0/
0%
0&
01
02
0)
0*
1+
0,
0-
1.
b0 #
b100100 "
b11010 $
#27
1)
1-
b110101 "
b11011 $
#28
10
13
b1001 #
b11100 $
#29
00
0)
0-
0.
b1000 #
b100 "
b11101 $
#30
10
03
0+
b1 #
b0 "
b11110 $
#31
1/
b11 !
14
1%
1&
1'
11
1)
1*
1+
1,
1-
1.
b11 #
b111111 "
b11111 $
#32
0/
b0 !
04
0%
0&
0'
01
13
0*
0,
0-
b1001 #
b100101 "
b100000 $
#33
b1 !
1/
1&
0)
1,
1-
b111100 "
b100001 $
#34
0/
b10 !
14
0&
1'
11
12
03
1*
0,
0-
b111 #
b100110 "
b100010 $
#35
02
b11 #
b100011 $
#36
b0 !
04
0'
01
12
0*
0+
1,
b101 #
b101000 "
b100100 $
#37
00
02
1)
1+
0.
b0 #
b1101 "
b100101 $
#38
11
13
1*
0+
0,
b1010 #
b11 "
b100110 $
#39
1/
b11 !
14
1&
1(
10
01
12
1,
1-
1.
b1101 #
b111011 "
b100111 $
#40
0&
1'
0(
1%
11
03
1+
0,
0-
b111 #
b100111 "
b101000 $
#41
0/
b0 !
04
0%
0'
01
02
13
0)
0*
b1001 #
b100100 "
b101001 $
#42
b10 !
14
1(
12
1*
0+
1,
0.
b1101 #
b1010 "
b101010 $
#43
b11 !
1/
1&
1'
0(
11
02
03
0*
1-
1.
b11 #
b111000 "
b101011 $
#44
b10 !
0/
0&
13
1*
0-
b1011 #
b101010 "
b101100 $
#45
0'
1(
00
01
12
1)
0*
1-
0.
b1100 #
b11001 "
b101101 $
#46
1*
0,
b10011 "
b101110 $
#47
04
b1 !
1/
0(
1%
10
03
1+
0-
1.
b101 #
b100111 "
b101111 $
#48
0/
b10 !
14
0%
1(
00
13
0*
1,
b1100 #
b101101 "
b110000 $
#49
b0 !
04
0(
10
02
0)
1*
0+
0,
1-
b1001 #
b110010 "
b110001 $
#50
00
11
03
1)
0*
b10 #
b110001 "
b110010 $
#51
01
12
1,
0-
b100 #
b101001 "
b110011 $
#52
b10 !
14
1'
10
11
02
13
1+
0,
0.
b1011 #
b101 "
b110100 $
#53
b11 !
1/
1%
0'
1(
01
12
1*
1,
b1101 #
b1111 "
b110101 $
#54
00
11
1-
b1110 #
b11111 "
b110110 $
#55
0/
b0 !
04
0%
0(
10
01
03
0)
0*
0,
0-
b101 #
b100 "
b110111 $
#56
b10 !
14
1'
11
02
1)
1*
0+
1,
1.
b11 #
b101011 "
b111000 $
#57
b0 !
04
0'
00
0)
0*
0,
b10 #
b100000 "
b111001 $
#58
b10 !
14
1'
10
1)
1*
1,
1-
0.
b11 #
b11011 "
b111010 $
#59
04
b0 !
0/
0'
0&
00
12
0,
1.
b110 #
b110011 "
b111011 $
#60
02
0-
0.
b10 #
b11 "
b111100 $
#61
b0 !
0/
0%
01
0)
1+
b0 #
b110 "
b111101 $
#62
10
12
1)
0*
0+
b101 #
b1 "
b111110 $
#63
b10 !
14
1'
11
02
13
1*
1-
1.
b1011 #
b110011 "
b111111 $
#64
b0 !
04
0'
00
03
0*
0.
b10 #
b10001 "
b1000000 $
#65
01
0)
1+
1,
b0 #
b11100 "
b1000001 $
#66
10
12
1)
0,
b101 #
b10101 "
b1000010 $
#67
00
02
0)
1*
0+
1,
0-
b0 #
b1010 "
b1000011 $
#68
b10 !
14
1'
10
11
1)
0*
0,
1.
b11 #
b100001 "
b1000100 $
#69
b0 !
04
0'
00
12
0)
1*
1+
b110 #
b100110 "
b1000101 $
#70
10
01
02
13
0*
1-
0.
b1001 #
b10100 "
b1000110 $
#71
b10 !
14
1'
11
03
1)
1,
b11 #
b11101 "
b1000111 $
#72
1(
12
13
1*
0+
0,
b1111 #
b10011 "
b1001000 $
#73
04
b0 !
0/
0'
0(
0%
00
02
0)
0*
1+
1,
0-
1.
b1010 #
b101100 "
b1001001 $
#74
01
03
1*
b0 #
b101110 "
b1001010 $
#75
b10 !
14
1(
11
12
13
1)
0+
0,
1-
0.
b1110 #
b10011 "
b1001011 $
#76
1/
b1 !
04
1&
0(
02
0)
0*
1,
1.
b1010 #
b111000 "
b1001100 $
#77
14
b10 !
0/
1'
0&
10
1)
1*
0,
0-
0.
b1011 #
b11 "
b1001101 $
#78
b11 !
1/
1&
0'
1(
0%
01
12
0*
1+
1,
1-
1.
b1101 #
b111101 "
b1001110 $
#79
0)
b111100 "
b1001111 $
#80
b1 !
04
0(
02
0+
b1001 #
b111000 "
b1010000 $
#81
1%
b1 !
1/
0&
00
11
12
03
1)
1*
1+
0,
0-
0.
b110 #
b111 "
b1010001 $
#82
14
b10 !
0/
1(
0%
10
01
13
0)
0+
1,
1.
b1101 #
b101010 "
b1010010 $
#83
1'
0(
11
02
03
0*
1+
b11 #
b101100 "
b1010011 $
#84
b0 !
04
0'
00
01
13
0,
1-
0.
b1000 #
b10100 "
b1010100 $
#85
b10 !
14
1(
11
12
1)
1*
0+
0-
1.
b1110 #
b100011 "
b1010101 $
#86
b11 !
1/
1%
1+
1,
b101111 "
b1010110 $
#87
b10 !
0/
1'
0(
0%
10
02
03
0)
0*
0+
0,
b11 #
b100000 "
b1010111 $
#88
13
b1011 #
b1011000 $
#89
b0 !
04
0'
00
01
03
b0 #
b1011001 $
#90
1+
0.
b100 "
b1011010 $
#91
12
1)
b100 #
b101 "
b1011011 $
#92
b10 !
14
1'
1(
10
11
13
1*
0+
1-
b1111 #
b10011 "
b1011100 $
#93
b10 !
0/
0(
0%
02
0)
1+
b1011 #
b10110 "
b1011101 $
#94
0'
1(
00
12
0*
0-
b1110 #
b100 "
b1011110 $
#95
b0 !
04
0(
10
01
02
03
1)
1.
b1 #
b100101 "
b1011111 $
#96
00
11
12
1*
0+
1,
1-
0.
b110 #
b11011 "
b1100000 $
#97
01
02
13
0*
0-
b1000 #
b1001 "
b1100001 $
#98
b10 !
14
1'
1(
10
11
12
0)
1+
1-
b1111 #
b11100 "
b1100010 $
#99
b10 !
0/
0(
0&
02
1)
0,
1.
b1011 #
b110101 "
b1100011 $
#100
b1100100 $
