homework/homework03/byteInv/byteInv.v
module byteInv (
    in, 
    out
);

input [31:0] in;
output [31:0] out;

assign out = {in[7:0], in[15:8], in[23:16], in[31:24]};
    
endmodule

homework/homework03/task-1-2-byteInv/test_byteInv.v
`include "byteInv.v"

module test (

);

reg [31:0] a;
wire [31:0] b;

byteInv u_byte(
    .in(a),
    .out(b)
);

reg [31:0] in_test [99:0];
reg [31:0] out_test [99:0];

integer i;

initial begin
    $dumpfile("test_byte.vcd");
    $dumpvars;
    $readmemh("byteInv.in", in_test);
    $readmemh("byteInv.out", out_test);
    for (i = 0; i < 100; i = 1 + i) begin
        a = in_test[i];
        #1;
        if (b !== out_test[i]) begin
            $display("test failed at %d! in: %08x, out: %08x, should: %08x", i, a, b, out_test[i]);
            // $finish;
        end
    end
    #1;
    $display("test passed");
    $finish;
end

endmodule

homework/homework03/byteInv/test_byte.vcd
$date
	Thu Sep 24 10:22:09 2020
$end
$version
	Icarus Verilog
$end
$timescale
	1s
$end
$scope module test $end
$var wire 32 ! b [31:0] $end
$var reg 32 " a [31:0] $end
$var integer 32 # i [31:0] $end
$scope module u_byte $end
$var wire 32 $ in [31:0] $end
$var wire 32 % out [31:0] $end
$upscope $end
$upscope $end
$enddefinitions $end
#0
$dumpvars
b10111010100100101010110111000111 %
b11000111101011011001001010111010 $
b0 #
b11000111101011011001001010111010 "
b10111010100100101010110111000111 !
$end
#1
b110000111111110111100111011100 !
b110000111111110111100111011100 %
b11011100011110011111111100110000 "
b11011100011110011111111100110000 $
b1 #
#2
b10011100001001100101011100100010 !
b10011100001001100101011100100010 %
b100010010101110010011010011100 "
b100010010101110010011010011100 $
b10 #
#3
b10101000110010010101001010010001 !
b10101000110010010101001010010001 %
b10010001010100101100100110101000 "
b10010001010100101100100110101000 $
b11 #
#4
b10000001001000110110000111111000 !
b10000001001000110110000111111000 %
b11111000011000010010001110000001 "
b11111000011000010010001110000001 $
b100 #
#5
b10101110101101001001110001100010 !
b10101110101101001001110001100010 %
b1100010100111001011010010101110 "
b1100010100111001011010010101110 $
b101 #
#6
b10010110110010100110000111100010 !
b10010110110010100110000111100010 %
b11100010011000011100101010010110 "
b11100010011000011100101010010110 $
b110 #
#7
b11000001000010100101111010111111 !
b11000001000010100101111010111111 %
b10111111010111100000101011000001 "
b10111111010111100000101011000001 $
b111 #
#8
b11001110011000110110010011011101 !
b11001110011000110110010011011101 %
b11011101011001000110001111001110 "
b11011101011001000110001111001110 $
b1000 #
#9
b10000010101110000111001101111101 !
b10000010101110000111001101111101 %
b1111101011100111011100010000010 "
b1111101011100111011100010000010 $
b1001 #
#10
b1001110001110111011011110111011 !
b1001110001110111011011110111011 %
b10111011101101110011101101001110 "
b10111011101101110011101101001110 $
b1010 #
#11
b1000111001110011010000001101010 !
b1000111001110011010000001101010 %
b1101010101000000011100101000111 "
b1101010101000000011100101000111 $
b1011 #
#12
b10000110010110000001000000100010 !
b10000110010110000001000000100010 %
b100010000100000101100010000110 "
b100010000100000101100010000110 $
b1100 #
#13
b1001010010010100110010011101100 !
b1001010010010100110010011101100 %
b11101100011001000100101001001010 "
b11101100011001000100101001001010 $
b1101 #
#14
b1110101001101111111011101011111 !
b1110101001101111111011101011111 %
b1011111111101110011011101110101 "
b1011111111101110011011101110101 $
b1110 #
#15
b1011111110110101000011000010100 !
b1011111110110101000011000010100 %
b10100100001101101101001011111 "
b10100100001101101101001011111 $
b1111 #
#16
b10100011101110000101101110001111 !
b10100011101110000101101110001111 %
b10001111010110111011100010100011 "
b10001111010110111011100010100011 $
b10000 #
#17
b1100000110110101101011010101 !
b1100000110110101101011010101 %
b11010101010110100001101100001100 "
b11010101010110100001101100001100 $
b10001 #
#18
b11111001010110110001011010111111 !
b11111001010110110001011010111111 %
b10111111000101100101101111111001 "
b10111111000101100101101111111001 $
b10010 #
#19
b1111011111101110101110011100001 !
b1111011111101110101110011100001 %
b11100001010111001111011101111011 "
b11100001010111001111011101111011 $
b10011 #
#20
b10111100010100001100110101101111 !
b10111100010100001100110101101111 %
b1101111110011010101000010111100 "
b1101111110011010101000010111100 $
b10100 #
#21
b1111110101001001010100000100000 !
b1111110101001001010100000100000 %
b100000101010001010010001111110 "
b100000101010001010010001111110 $
b10101 #
#22
b10100001011101001111111000010100 !
b10100001011101001111111000010100 %
b10100111111100111010010100001 "
b10100111111100111010010100001 $
b10110 #
#23
b10011100110100111010100000100001 !
b10011100110100111010100000100001 %
b100001101010001101001110011100 "
b100001101010001101001110011100 $
b10111 #
#24
b11100100010100001001010100011111 !
b11100100010100001001010100011111 %
b11111100101010101000011100100 "
b11111100101010101000011100100 $
b11000 #
#25
b10001011110101000111000100101000 !
b10001011110101000111000100101000 %
b101000011100011101010010001011 "
b101000011100011101010010001011 $
b11001 #
#26
b10111001001001011101100001011101 !
b10111001001001011101100001011101 %
b1011101110110000010010110111001 "
b1011101110110000010010110111001 $
b11010 #
#27
b1101001000001111001100011001111 !
b1101001000001111001100011001111 %
b11001111100110000000011101101001 "
b11001111100110000000011101101001 $
b11011 #
#28
b11011011010010010111011100111111 !
b11011011010010010111011100111111 %
b111111011101110100100111011011 "
b111111011101110100100111011011 $
b11100 #
#29
b1100000101000100000010001101100 !
b1100000101000100000010001101100 %
b1101100000001001010001001100000 "
b1101100000001001010001001100000 $
b11101 #
#30
b10011010010100001010100110011001 !
b10011010010100001010100110011001 %
b10011001101010010101000010011010 "
b10011001101010010101000010011010 $
b11110 #
#31
b11111110100110011101110111000101 !
b11111110100110011101110111000101 %
b11000101110111011001100111111110 "
b11000101110111011001100111111110 $
b11111 #
#32
b11001100101011010111001011001101 !
b11001100101011010111001011001101 %
b11001101011100101010110111001100 "
b11001101011100101010110111001100 $
b100000 #
#33
b1101101000111111101110101010000 !
b1101101000111111101110101010000 %
b1010000110111010001111101101101 "
b1010000110111010001111101101101 $
b100001 #
#34
b100011100001100010111110010100 !
b100011100001100010111110010100 %
b10010100001011111000011000100011 "
b10010100001011111000011000100011 $
b100010 #
#35
b1001001011011111111101101111111 !
b1001001011011111111101101111111 %
b1111111111110110110111101001001 "
b1111111111110110110111101001001 $
b100011 #
#36
b10001000110000110011011010011100 !
b10001000110000110011011010011100 %
b10011100001101101100001110001000 "
b10011100001101101100001110001000 $
b100100 #
#37
b10011001001001000000111001011110 !
b10011001001001000000111001011110 %
b1011110000011100010010010011001 "
b1011110000011100010010010011001 $
b100101 #
#38
b10001000110111001101010011000100 !
b10001000110111001101010011000100 %
b11000100110101001101110010001000 "
b11000100110101001101110010001000 $
b100110 #
#39
b11001110110111011101111000111100 !
b11001110110111011101111000111100 %
b111100110111101101110111001110 "
b111100110111101101110111001110 $
b100111 #
#40
b1000101011001100111001110110011 !
b1000101011001100111001110110011 %
b10110011011100110110011001000101 "
b10110011011100110110011001000101 $
b101000 #
#41
b110000010111011110110010111 !
b110000010111011110110010111 %
b10010111101111010000101100000110 "
b10010111101111010000101100000110 $
b101001 #
#42
b101011011000010111110001000110 !
b101011011000010111110001000110 %
b1000110011111000110000100101011 "
b1000110011111000110000100101011 $
b101010 #
#43
b10010011100100111001110101111011 !
b10010011100100111001110101111011 %
b1111011100111011001001110010011 "
b1111011100111011001001110010011 $
b101011 #
#44
b11011111001010011011110100111010 !
b11011111001010011011110100111010 %
b111010101111010010100111011111 "
b111010101111010010100111011111 $
b101100 #
#45
b1111010101100000110110010111 !
b1111010101100000110110010111 %
b10010111000011010101011000001111 "
b10010111000011010101011000001111 $
b101101 #
#46
b10011010100000100000011001110000 !
b10011010100000100000011001110000 %
b1110000000001101000001010011010 "
b1110000000001101000001010011010 $
b101110 #
#47
b11101101001110000111010111101101 !
b11101101001110000111010111101101 %
b11101101011101010011100011101101 "
b11101101011101010011100011101101 $
b101111 #
#48
b1110010010011111111001101010000 !
b1110010010011111111001101010000 %
b1010000111100110100111101110010 "
b1010000111100110100111101110010 $
b110000 #
#49
b10001101011110001111110111011100 !
b10001101011110001111110111011100 %
b11011100111111010111100010001101 "
b11011100111111010111100010001101 $
b110001 #
#50
b1001010011010000100111111011110 !
b1001010011010000100111111011110 %
b11011110010011110110100001001010 "
b11011110010011110110100001001010 $
b110010 #
#51
b1000011101100111110101100111100 !
b1000011101100111110101100111100 %
b111100111010111011001101000011 "
b111100111010111011001101000011 $
b110011 #
#52
b11111100010010100100011011111011 !
b11111100010010100100011011111011 %
b11111011010001100100101011111100 "
b11111011010001100100101011111100 $
b110100 #
#53
b1000010100010001101000101011 !
b1000010100010001101000101011 %
b101011000110100101000100001000 "
b101011000110100101000100001000 $
b110101 #
#54
b10001000100100100110100011110001 !
b10001000100100100110100011110001 %
b11110001011010001001001010001000 "
b11110001011010001001001010001000 $
b110110 #
#55
b1000010101111110001011001110110 !
b1000010101111110001011001110110 %
b1110110000101101011111101000010 "
b1110110000101101011111101000010 $
b110111 #
#56
b1001111010000110000010010111001 !
b1001111010000110000010010111001 %
b10111001000001000100001101001111 "
b10111001000001000100001101001111 $
b111000 #
#57
b100101110011000100100101011011 !
b100101110011000100100101011011 %
b1011011010010011100110000100101 "
b1011011010010011100110000100101 $
b111001 #
#58
b1010011101000110100010110011111 !
b1010011101000110100010110011111 %
b10011111010001011010001101010011 "
b10011111010001011010001101010011 $
b111010 #
#59
b1100111000100100001000100110100 !
b1100111000100100001000100110100 %
b110100000100010001001001100111 "
b110100000100010001001001100111 $
b111011 #
#60
b111000111100101101000010110011 !
b111000111100101101000010110011 %
b10110011110100001111001000111000 "
b10110011110100001111001000111000 $
b111100 #
#61
b1000010101110010110000111000111 !
b1000010101110010110000111000111 %
b11000111011000011011100101000010 "
b11000111011000011011100101000010 $
b111101 #
#62
b1001101111111010110011110111 !
b1001101111111010110011110111 %
b11110111101011001011111100001001 "
b11110111101011001011111100001001 $
b111110 #
#63
b111011001110011011010100001011 !
b111011001110011011010100001011 %
b1011101101010011100100111011 "
b1011101101010011100100111011 $
b111111 #
#64
b11100110000010100001100111000100 !
b11100110000010100001100111000100 %
b11000100000110010000101011100110 "
b11000100000110010000101011100110 $
b1000000 #
#65
b11000110100111110110110010110010 !
b11000110100111110110110010110010 %
b10110010011011001001111111000110 "
b10110010011011001001111111000110 $
b1000001 #
#66
b1001011000000001010100011111010 !
b1001011000000001010100011111010 %
b11111010101010000000000001001011 "
b11111010101010000000000001001011 $
b1000010 #
#67
b1001010111000110111011111110100 !
b1001010111000110111011111110100 %
b11110100011101111110001101001010 "
b11110100011101111110001101001010 $
b1000011 #
#68
b10101101100100010111010101011100 !
b10101101100100010111010101011100 %
b1011100011101011001000110101101 "
b1011100011101011001000110101101 $
b1000100 #
#69
b1111101001100011100100010110111 !
b1111101001100011100100010110111 %
b10110111110010000011000101111101 "
b10110111110010000011000101111101 $
b1000101 #
#70
b11100010001010010100000000100001 !
b11100010001010010100000000100001 %
b100001010000000010100111100010 "
b100001010000000010100111100010 $
b1000110 #
#71
b11011000101000101111000111101001 !
b11011000101000101111000111101001 %
b11101001111100011010001011011000 "
b11101001111100011010001011011000 $
b1000111 #
#72
b1000110000110001011001001101011 !
b1000110000110001011001001101011 %
b1101011101100100001100001000110 "
b1101011101100100001100001000110 $
b1001000 #
#73
b10101110110010100110011111001010 !
b10101110110010100110011111001010 %
b11001010011001111100101010101110 "
b11001010011001111100101010101110 $
b1001001 #
#74
b1101110111011000010100000101110 !
b1101110111011000010100000101110 %
b101110001010001110110001101110 "
b101110001010001110110001101110 $
b1001010 #
#75
b11110010111100100010001110001 !
b11110010111100100010001110001 %
b1110001010001000101111000011110 "
b1110001010001000101111000011110 $
b1001011 #
#76
b100110110000110100010110110 !
b100110110000110100010110110 %
b10110110011010001101100000000100 "
b10110110011010001101100000000100 $
b1001100 #
#77
b111101011001001001100000110001 !
b111101011001001001100000110001 %
b110001100110000110010000111101 "
b110001100110000110010000111101 $
b1001101 #
#78
b111011101000111111010011111110 !
b111011101000111111010011111110 %
b11111110111101001010001100111011 "
b11111110111101001010001100111011 $
b1001110 #
#79
b11001111010001011000011010010100 !
b11001111010001011000011010010100 %
b10010100100001100100010111001111 "
b10010100100001100100010111001111 $
b1001111 #
#80
b11110001011100000001111101100011 !
b11110001011100000001111101100011 %
b1100011000111110111000011110001 "
b1100011000111110111000011110001 $
b1010000 #
#81
b10001000000011111011111001111110 !
b10001000000011111011111001111110 %
b1111110101111100000111110001000 "
b1111110101111100000111110001000 $
b1010001 #
#82
b10011111100000000000110101100001 !
b10011111100000000000110101100001 %
b1100001000011011000000010011111 "
b1100001000011011000000010011111 $
b1010010 #
#83
b10110010010101011100110101110100 !
b10110010010101011100110101110100 %
b1110100110011010101010110110010 "
b1110100110011010101010110110010 $
b1010011 #
#84
b11001101110010101010111101001 !
b11001101110010101010111101001 %
b11101001010101011011100100011001 "
b11101001010101011011100100011001 $
b1010100 #
#85
b1011111000010001000000001000 !
b1011111000010001000000001000 %
b1000000100001110000100001011 "
b1000000100001110000100001011 $
b1010101 #
#86
b10100110000111101011111110100001 !
b10100110000111101011111110100001 %
b10100001101111110001111010100110 "
b10100001101111110001111010100110 $
b1010110 #
#87
b11110011100000110110011111010100 !
b11110011100000110110011111010100 %
b11010100011001111000001111110011 "
b11010100011001111000001111110011 $
b1010111 #
#88
b11000101001010011000101010110001 !
b11000101001010011000101010110001 %
b10110001100010100010100111000101 "
b10110001100010100010100111000101 $
b1011000 #
#89
b10100101100111101011000001000111 !
b10100101100111101011000001000111 %
b1000111101100001001111010100101 "
b1000111101100001001111010100101 $
b1011001 #
#90
b10010110011110101000010001101011 !
b10010110011110101000010001101011 %
b1101011100001000111101010010110 "
b1101011100001000111101010010110 $
b1011010 #
#91
b10101001000010110101111010011110 !
b10101001000010110101111010011110 %
b10011110010111100000101110101001 "
b10011110010111100000101110101001 $
b1011011 #
#92
b1111111000100000110111011111001 !
b1111111000100000110111011111001 %
b11111001011011100001000001111111 "
b11111001011011100001000001111111 $
b1011100 #
#93
b10000110101110001011011110011100 !
b10000110101110001011011110011100 %
b10011100101101111011100010000110 "
b10011100101101111011100010000110 $
b1011101 #
#94
b10010001110000011110010100111100 !
b10010001110000011110010100111100 %
b111100111001011100000110010001 "
b111100111001011100000110010001 $
b1011110 #
#95
b1010001110011011000011011101111 !
b1010001110011011000011011101111 %
b11101111100001101100110101010001 "
b11101111100001101100110101010001 $
b1011111 #
#96
b1000101101111010001001010011001 !
b1000101101111010001001010011001 %
b10011001000100101011110101000101 "
b10011001000100101011110101000101 $
b1100000 #
#97
b110100111110110000111101010000 !
b110100111110110000111101010000 %
b1010000000011111111101100110100 "
b1010000000011111111101100110100 $
b1100001 #
#98
b1101010001111011010010110 !
b1101010001111011010010110 %
b10010110111101101010100000000001 "
b10010110111101101010100000000001 $
b1100010 #
#99
b11010001011100001010001110111011 !
b11010001011100001010001110111011 %
b10111011101000110111000011010001 "
b10111011101000110111000011010001 $
b1100011 #
#100
b1100100 #
