homework/homework09/mealy/mealy.v
module  seqdet_mealy (
    clk, 
    reset,
    data,
    res
);


`define idle 0 
`define state1 1
`define state10 2
`define state100 3
`define state1001 4

input clk, reset, data;
output res;

assign res = res_reg;

reg res_reg;
reg [3:0] status;


always @(posedge clk or reset) begin
    if (reset) begin
        status <= `idle;
        res_reg <= 0;
    end
    else begin
        case (status)
            `idle: begin
                if (data == 1) begin
                    status <= `state1;
                    
                end
                else begin
                    status <= `idle;
                    res_reg <= 0;      
                end
                
            end
            `state1: begin
                if (data == 1) begin
                    status <= `state1;
                    res_reg <= 0;
                end 
                else begin
                    status <= `state10; 
                    res_reg <= 0;
                end
            end
            `state10: begin
                if (data == 1) begin
                    status <= `state1; 
                    res_reg <= 0;
                end
                else begin
                    status <= `state100;
                    res_reg <= 0;
                end
            end
            `state100: begin
                if (data == 1) begin
                    status <= `state1001;
                    res_reg <= 0;
                end
                else begin
                    status <= `idle;  
                    res_reg <= 0;
                end
            end
            `state1001: begin
                if (data == 1) begin
                    status <= `state1;
                    res_reg <= 0;
                end
                else begin
                    status <= `state10; 
                    res_reg <= 1;
                end
            end
            default: begin
                status <= `idle;
                res_reg <= 0;
            end
        endcase
    end
end
    
endmodule

homework/homework09/mealy/mealy_tb.v
`include "mealy.v"

module test (
);

reg clk, reset, data;
wire res;

seqdet_mealy u(
    clk,
    reset,
    data,
    res
);

always #1 clk = ~clk;

integer i;
reg all [19:0];

initial begin
    $dumpfile("test.vcd");
    $dumpvars;
    reset = 1;
    clk = 0;
    #1 reset = 0;
    #1;
    $readmemb("data.bin", all);
    for (i = 0; i < 20; i = i + 1) begin
        @( posedge clk);
        data = all[i];
    end
    #2 $finish;
end
    
endmodule

homework/homework09/mealy/test.vcd
$date
	Wed Nov  4 22:32:07 2020
$end
$version
	Icarus Verilog
$end
$timescale
	1s
$end
$scope module test $end
$var wire 1 ! res $end
$var reg 1 " clk $end
$var reg 1 # data $end
$var reg 1 $ reset $end
$var integer 32 % i [31:0] $end
$scope module u $end
$var wire 1 " clk $end
$var wire 1 # data $end
$var wire 1 ! res $end
$var wire 1 $ reset $end
$var reg 1 & res_reg $end
$var reg 4 ' status [3:0] $end
$upscope $end
$upscope $end
$enddefinitions $end
#0
$dumpvars
b0 '
0&
bx %
1$
x#
0"
0!
$end
#1
0$
1"
#2
b0 %
0"
#3
b1 %
0#
1"
#4
0"
#5
b1 '
b10 %
1#
1"
#6
0"
#7
b10 '
b11 %
0#
1"
#8
0"
#9
b11 '
b100 %
1"
#10
0"
#11
b100 '
b101 %
1#
1"
#12
0"
#13
b1 '
b110 %
1"
#14
0"
#15
b10 '
b111 %
0#
1"
#16
0"
#17
b1 '
b1000 %
1#
1"
#18
0"
#19
b10 '
b1001 %
0#
1"
#20
0"
#21
b11 '
b1010 %
1"
#22
0"
#23
b100 '
b1011 %
1#
1"
#24
0"
#25
1!
1&
b10 '
b1100 %
0#
1"
#26
0"
#27
0!
0&
b11 '
b1101 %
1"
#28
0"
#29
b100 '
b1110 %
1#
1"
#30
0"
#31
1!
1&
b10 '
b1111 %
0#
1"
#32
0"
#33
0!
0&
b1 '
b10000 %
1#
1"
#34
0"
#35
b10001 %
1"
#36
0"
#37
b10 '
b10010 %
0#
1"
#38
0"
#39
b1 '
b10011 %
1#
1"
#40
0"
#41
b10 '
b10100 %
0#
1"
#42
0"
#43
b11 '
1"
