homework/homework12/03led/sync.v
module sync (
    clk,
    reset,
    read,
    sig,
    valid
);

input clk, reset, sig, read;
output reg valid;
reg sig_buf;

always @(*) begin
    if (valid) begin
        sig_buf = 0;
    end
    else begin
        sig_buf = sig;
    end
end

always @(posedge clk or posedge reset) begin
    if (reset) begin
        valid <= 0;
    end
    else begin
        if (valid) begin
            if (read) begin
                valid <= 0;
            end
            else valid <= valid;
        end
        else begin
            if (sig_buf == 1) begin
                valid <= 1;
            end
            else begin
                valid <= 0;
            end 
        end
    end
end



endmodule

homework/homework12/03led/sync_tb.v
`include "sync.v"
module test (
);

reg clk, reset, read, sig;
wire valid;

 sync u(
    clk,
    reset,
    read,
    sig,
    valid
);

always #5 clk = ~clk;

initial begin
    $dumpfile("test.vcd");
    $dumpvars;
    clk = 0;
    reset = 0;
    read = 0;
    #1 reset = 1;
    #1 reset = 0;
    #23 sig = 1;
    #2 sig = 0;
    #30 read = 1;
    #10 read = 0;
    #200 $finish;
end
    
endmodule

homework/homework12/03led/test.vcd
$date
	Mon Nov 30 10:48:13 2020
$end
$version
	Icarus Verilog
$end
$timescale
	1s
$end
$scope module test $end
$var wire 1 ! valid $end
$var reg 1 " clk $end
$var reg 1 # read $end
$var reg 1 $ reset $end
$var reg 1 % sig $end
$scope module u $end
$var wire 1 " clk $end
$var wire 1 # read $end
$var wire 1 $ reset $end
$var wire 1 % sig $end
$var reg 1 & sig_buf $end
$var reg 1 ! valid $end
$upscope $end
$upscope $end
$enddefinitions $end
#0
$dumpvars
x&
x%
0$
0#
0"
x!
$end
#1
0!
1$
#2
0$
#5
1"
#10
0"
#15
1"
#20
0"
#25
1!
0&
1"
1%
#27
0%
#30
0"
#35
1"
#40
0"
#45
1"
#50
0"
#55
1"
#57
1#
#60
0"
#65
0!
1"
#67
0#
