homework/homework03/task1-3-adder/add32.v
`include "add16.v"
`define byname 0
// `define byport 0
`define addbit 32
`define Module_32 0

module add32 (
    a, b, cin, sum, cout
);
    

input [31:0] a, b;
input cin;
output [31:0] sum;
output cout;

wire [15:0] ah, al, bh, bl, sh, sl;
wire cout_l;

assign sum = {sh, sl};

`ifdef byport
add16 u_l(
    .a(al),
    .b(bl),
    .cin(cin),
    .sum(sl),
    .cout(cout_l)
);

add16 u_h(
    .a(ah),
    .b(bh),
    .cin(cout_l),
    .sum(sh),
    .cout(cout)
);
`endif


`ifdef byname
add16 u_l(
    al,
    bl,
    cin,
    sl,
    cout_l
);

add16 u_h(
    ah,
    bh,
    cout_l,
    sh,
    cout
);
`endif


endmodule

homework/homework03/task1-3-adder/add16.v
`define addbit 16
`define Module_16 0


module add16 (
    a, b, cin, sum, cout
);

input [15:0] a, b;
input cin;
output [15:0] sum;
output cout;

assign {cout, sum} = a + b + cin;


// initial begin
//     $display(`addbit);
// end
    
endmodule

homework/homework03/task1-3-adder/test.v
`include "add16.v"
// `include "add32.v"

module test (
);

reg [`addbit-1:0] a, b;
reg cin;
wire [`addbit:0] ans;

`ifdef Module_32 

add32 u_add(
    .a(a),
    .b(b),
    .cin(cin),
    .cout(ans[`addbit]),
    .sum(ans[`addbit - 1 : 0])
);

`else


add16 u_add(
    .a(a),
    .b(b),
    .cin(cin),
    .cout(ans[`addbit]),
    .sum(ans[`addbit - 1 : 0])
);

`endif 

reg [`addbit-1:0] a_test[99:0];
reg [`addbit-1:0] b_test[99:0];
reg cin_test [99:0];
reg [`addbit:0] ans_test[99:0];

integer i;

initial begin
    $dumpfile("test.vcd");
    $dumpvars;    
    $readmemb("add1.in", a_test);
    $readmemb("add2.in", b_test);
    $readmemb("cin.in", cin_test);
    $readmemb("ans.out", ans_test);

    for (i = 0; i < 100; i = i + 1) begin
        #1;
        a = a_test[i];
        b = b_test[i];
        cin = cin_test[i];
        #1;
        if (ans !== ans_test[i]) begin
            $display("test failed at %d! in1: %x in2: %x, cin: %x, out: %x, should: %x", i, a, b, cin, ans, ans_test[i]);
            $finish;
        end
    end
    $display("add %d test passed", `addbit);
    $finish;
end

endmodule

homework/homework03/task1-3-adder/test.vcd
$date
	Tue Sep 29 08:27:20 2020
$end
$version
	Icarus Verilog
$end
$timescale
	1s
$end
$scope module test $end
$var wire 17 ! ans [16:0] $end
$var reg 16 " a [15:0] $end
$var reg 16 # b [15:0] $end
$var reg 1 $ cin $end
$var integer 32 % i [31:0] $end
$scope module u_add $end
$var wire 16 & a [15:0] $end
$var wire 16 ' b [15:0] $end
$var wire 1 $ cin $end
$var wire 16 ( sum [15:0] $end
$var wire 1 ) cout $end
$upscope $end
$upscope $end
$enddefinitions $end
#0
$dumpvars
x)
bx (
bx '
bx &
b0 %
x$
bx #
bx "
bx !
$end
#1
b110111010110101 (
b10110111010110101 !
1)
1$
b1010100110000101 #
b1010100110000101 '
b1100010100101111 "
b1100010100101111 &
#2
b1 %
#3
b10010011101111110 !
b10011101111110 (
b11110001000010 #
b11110001000010 '
b1110101100111011 "
b1110101100111011 &
#4
b10 %
#5
b1100110110111010 (
b1100110110111010 !
0)
b100001101110000 #
b100001101110000 '
b1000101001001001 "
b1000101001001001 &
#6
b11 %
#7
1)
b10011010111010010 !
b11010111010010 (
b1000010100110100 #
b1000010100110100 '
b1011000010011101 "
b1011000010011101 &
#8
b100 %
#9
0)
b1100100101000010 !
b1100100101000010 (
0$
b100011101000011 #
b100011101000011 '
b1000000111111111 "
b1000000111111111 &
#10
b101 %
#11
1)
b10101110000000111 !
b101110000000111 (
b1101000110010011 #
b1101000110010011 '
b1000101001110100 "
b1000101001110100 &
#12
b110 %
#13
b10011101110100101 !
b11101110100101 (
b111010001110001 #
b111010001110001 '
b1100011100110100 "
b1100011100110100 &
#14
b111 %
#15
b111010101100000 (
b111010101100000 !
0)
b100011010101100 #
b100011010101100 '
b10111010110100 "
b10111010110100 &
#16
b1000 %
#17
1)
b11000011111111010 !
b1000011111111010 (
b1111010001001111 #
b1111010001001111 '
b1001001110101011 "
b1001001110101011 &
#18
b1001 %
#19
b10100101001000011 !
b100101001000011 (
1$
b1000100010110110 #
b1000100010110110 '
b1100000110001100 "
b1100000110001100 &
#20
b1010 %
#21
b10010011101110111 !
b10011101110111 (
b101100111101101 #
b101100111101101 '
b1100110110001001 "
b1100110110001001 &
#22
b1011 %
#23
b1010111110110110 (
b1010111110110110 !
0)
b1010101001110100 #
b1010101001110100 '
b10101000001 "
b10101000001 &
#24
b1100 %
#25
b1101010111010110 !
b1101010111010110 (
0$
b1000011100000110 #
b1000011100000110 '
b100111011010000 "
b100111011010000 &
#26
b1101 %
#27
1)
b10000111101001110 !
b111101001110 (
b1101100001111000 #
b1101100001111000 '
b11011011010110 "
b11011011010110 &
#28
b1110 %
#29
b11000000001000111 !
b1000000001000111 (
1$
b1101000011110010 #
b1101000011110010 '
b1010111101010100 "
b1010111101010100 &
#30
b1111 %
#31
0)
b1110101100111100 !
b1110101100111100 (
0$
b101010000101111 #
b101010000101111 '
b1001011100001101 "
b1001011100001101 &
#32
b10000 %
#33
b1111110110100000 !
b1111110110100000 (
1$
b110110001110011 #
b110110001110011 '
b1001000100101100 "
b1001000100101100 &
#34
b10001 %
#35
b1011000100010101 !
b1011000100010101 (
b101111110101001 #
b101111110101001 '
b101000101101011 "
b101000101101011 &
#36
b10010 %
#37
b1111001101110001 (
b11111001101110001 !
1)
0$
b1111110011010010 #
b1111110011010010 '
b1111011010011111 "
b1111011010011111 &
#38
b10011 %
#39
0)
b1110110010010011 !
b1110110010010011 (
1$
b1000011100111010 #
b1000011100111010 '
b110010101011000 "
b110010101011000 &
#40
b10100 %
#41
b1001010110101111 (
b11001010110101111 !
1)
0$
b1010011100011011 #
b1010011100011011 '
b1110111010010100 "
b1110111010010100 &
#42
b10101 %
#43
b1001001001011101 (
b1001001001011101 !
0)
1$
b100111001001100 #
b100111001001100 '
b100010000010000 "
b100010000010000 &
#44
b10110 %
#45
b1110110011111011 !
b1110110011111011 (
b11001100011100 #
b11001100011100 '
b1011100111011110 "
b1011100111011110 &
#46
b10111 %
#47
b1100100000111000 (
b11100100000111000 !
1)
b1110100011110011 #
b1110100011110011 '
b1101111101000100 "
b1101111101000100 &
#48
b11000 %
#49
0)
b1110011000001001 !
b1110011000001001 (
b1010010001001011 #
b1010010001001011 '
b100000110111101 "
b100000110111101 &
#50
b11001 %
#51
b1101011101011110 !
b1101011101011110 (
b1000111111001 #
b1000111111001 '
b1100010101100100 "
b1100010101100100 &
#52
b11010 %
#53
1)
b11010000110011101 !
b1010000110011101 (
0$
b1110001101001011 #
b1110001101001011 '
b1011111001010010 "
b1011111001010010 &
#54
b11011 %
#55
b1100011100101001 (
b1100011100101001 !
0)
b1011011111101100 #
b1011011111101100 '
b111100111101 "
b111100111101 &
#56
b11100 %
#57
b1100101111111101 !
b1100101111111101 (
1$
b101000111110 #
b101000111110 '
b1100000110111110 "
b1100000110111110 &
#58
b11101 %
#59
b1101101111100111 !
b1101101111100111 (
0$
b1011010000101101 #
b1011010000101101 '
b10011110111010 "
b10011110111010 &
#60
b11110 %
#61
b11110111000000 (
b10011110111000000 !
1)
1$
b1010100010100111 #
b1010100010100111 '
b1001010100011000 "
b1001010100011000 &
#62
b11111 %
#63
b1011100010001100 (
b1011100010001100 !
0)
b110110111001010 #
b110110111001010 '
b100101011000001 "
b100101011000001 &
#64
b100000 %
#65
b1000111011001100 !
b1000111011001100 (
0$
b100101001101101 #
b100101001101101 '
b100010001011111 "
b100010001011111 &
#66
b100001 %
#67
b1011111111010001 !
b1011111111010001 (
1$
b100111111010 #
b100111111010 '
b1011010111010110 "
b1011010111010110 &
#68
b100010 %
#69
b1100011111110111 !
b1100011111110111 (
0$
b1100010100000010 #
b1100010100000010 '
b1011110101 "
b1011110101 &
#70
b100011 %
#71
b1011000011000111 (
b11011000011000111 !
1)
b1100111001111010 #
b1100111001111010 '
b1110001001001101 "
b1110001001001101 &
#72
b100100 %
#73
0)
b1101111000000111 !
b1101111000000111 (
b1001010001101 #
b1001010001101 '
b1100101101111010 "
b1100101101111010 &
#74
b100101 %
#75
b1010000100101100 !
b1010000100101100 (
1$
b111110101101010 #
b111110101101010 '
b10001111000001 "
b10001111000001 &
#76
b100110 %
#77
b101000000110101 !
b101000000110101 (
b111110001000 #
b111110001000 '
b100000010101100 "
b100000010101100 &
#78
b100111 %
#79
1)
b10010111000110001 !
b10111000110001 (
b111101000011010 #
b111101000011010 '
b1011010000010110 "
b1011010000010110 &
#80
b101000 %
#81
b1001100000110010 (
b1001100000110010 !
0)
0$
b111100000010011 #
b111100000010011 '
b10000000011111 "
b10000000011111 &
#82
b101001 %
#83
b1100110110011101 !
b1100110110011101 (
1$
b1100100101100000 #
b1100100101100000 '
b10000111100 "
b10000111100 &
#84
b101010 %
#85
b111000101010000 (
b10111000101010000 !
1)
0$
b1011001011110001 #
b1011001011110001 '
b1011111001011111 "
b1011111001011111 &
#86
b101011 %
#87
0)
b1101001100111111 !
b1101001100111111 (
1$
b1100101011101 #
b1100101011101 '
b1011100111100001 "
b1011100111100001 &
#88
b101100 %
#89
b1010111001100000 !
b1010111001100000 (
b1010101001011011 #
b1010101001011011 '
b10000000100 "
b10000000100 &
#90
b101101 %
#91
b1011010100011101 !
b1011010100011101 (
0$
b1111000101011 #
b1111000101011 '
b1001011011110010 "
b1001011011110010 &
#92
b101110 %
#93
1)
b10100000010011010 !
b100000010011010 (
1$
b1111110100000011 #
b1111110100000011 '
b100001110010110 "
b100001110010110 &
#94
b101111 %
#95
0)
b1001000101000110 !
b1001000101000110 (
b11011000110100 #
b11011000110100 '
b101101100010001 "
b101101100010001 &
#96
b110000 %
#97
1)
b10001110110100110 !
b1110110100110 (
0$
b1101110100010101 #
b1101110100010101 '
b100000010010001 "
b100000010010001 &
#98
b110001 %
#99
b10000110110100101 !
b110110100101 (
1$
b100011011010000 #
b100011011010000 '
b1100011011010100 "
b1100011011010100 &
#100
b110010 %
#101
b110001111101101 (
b110001111101101 !
0)
b11000000100101 #
b11000000100101 '
b11001111000111 "
b11001111000111 &
#102
b110011 %
#103
b10111101001111 !
b10111101001111 (
b10011001000000 #
b10011001000000 '
b100100001110 "
b100100001110 &
#104
b110100 %
#105
b1100000110101011 !
b1100000110101011 (
b1100000011001110 #
b1100000011001110 '
b11011100 "
b11011100 &
#106
b110101 %
#107
b1100111000001110 !
b1100111000001110 (
b10100110110101 #
b10100110110101 '
b1010010001011000 "
b1010010001011000 &
#108
b110110 %
#109
1)
b10101111111000101 !
b101111111000101 (
b1111101111110001 #
b1111101111110001 '
b110001111010011 "
b110001111010011 &
#110
b110111 %
#111
b10011001101001111 !
b11001101001111 (
b110100011010111 #
b110100011010111 '
b1100101001110111 "
b1100101001110111 &
#112
b111000 %
#113
b10111100111011 (
b10111100111011 !
0)
0$
b1010111111010 #
b1010111111010 '
b1100101000001 "
b1100101000001 &
#114
b111001 %
#115
1)
b10000001101101010 !
b1101101010 (
1$
b1001011001101010 #
b1001011001101010 '
b110110011111111 "
b110110011111111 &
#116
b111010 %
#117
b10100011000001100 !
b100011000001100 (
b1110111011101111 #
b1110111011101111 '
b101011100011100 "
b101011100011100 &
#118
b111011 %
#119
0)
b1110000110001111 !
b1110000110001111 (
b1100000010111001 #
b1100000010111001 '
b10000011010101 "
b10000011010101 &
#120
b111100 %
#121
b10011000011100 (
b10010011000011100 !
1)
b1011111011001111 #
b1011111011001111 '
b110011101001100 "
b110011101001100 &
#122
b111101 %
#123
0)
b100011101000111 !
b100011101000111 (
b100000010 #
b100000010 '
b100011001000100 "
b100011001000100 &
#124
b111110 %
#125
b1111100001011000 !
b1111100001011000 (
b1110010101100010 #
b1110010101100010 '
b1001011110101 "
b1001011110101 &
#126
b111111 %
#127
b100010001100011 (
b10100010001100011 !
1)
b100010011110111 #
b100010011110111 '
b1111111101101011 "
b1111111101101011 &
#128
b1000000 %
#129
b1100000010011 (
b1100000010011 !
0)
b1000111110101 #
b1000111110101 '
b11000011101 "
b11000011101 &
#130
b1000001 %
#131
1)
b10110010110010101 !
b110010110010101 (
0$
b1100100010011010 #
b1100100010011010 '
b1001110011111011 "
b1001110011111011 &
#132
b1000010 %
#133
b11001001001010011 !
b1001001001010011 (
1$
b1101100011001101 #
b1101100011001101 '
b1011100110000101 "
b1011100110000101 &
#134
b1000011 %
#135
0)
b1111010000110010 !
b1111010000110010 (
b1011100010001101 #
b1011100010001101 '
b11101110100100 "
b11101110100100 &
#136
b1000100 %
#137
b110001000000011 (
b10110001000000011 !
1)
b1100101011000000 #
b1100101011000000 '
b1001011101000010 "
b1001011101000010 &
#138
b1000101 %
#139
0)
b1011000001010010 !
b1011000001010010 (
0$
b10010101001011 #
b10010101001011 '
b1000101100000111 "
b1000101100000111 &
#140
b1000110 %
#141
b1000110001001001 !
b1000110001001001 (
1$
b10001010100101 #
b10001010100101 '
b110100110100011 "
b110100110100011 &
#142
b1000111 %
#143
1)
b10010101101001100 !
b10101101001100 (
0$
b1100000110001010 #
b1100000110001010 '
b110100111000010 "
b110100111000010 &
#144
b1001000 %
#145
b10011100000010011 !
b11100000010011 (
1$
b1000011010111000 #
b1000011010111000 '
b1011000101011010 "
b1011000101011010 &
#146
b1001001 %
#147
b10110011000000011 !
b110011000000011 (
b111111011011001 #
b111111011011001 '
b1110011100101001 "
b1110011100101001 &
#148
b1001010 %
#149
b10001101000111110 !
b1101000111110 (
b101111111000110 #
b101111111000110 '
b1011101001110111 "
b1011101001110111 &
#150
b1001011 %
#151
b10100001111101110 !
b100001111101110 (
b1001011011001000 #
b1001011011001000 '
b1010110100100101 "
b1010110100100101 &
#152
b1001100 %
#153
b1110110111101011 (
b1110110111101011 !
0)
b1011000101011101 #
b1011000101011101 '
b11110010001101 "
b11110010001101 &
#154
b1001101 %
#155
b1111011111110110 !
b1111011111110110 (
b101000011111010 #
b101000011111010 '
b1010011011111011 "
b1010011011111011 &
#156
b1001110 %
#157
b1101011100110000 !
b1101011100110000 (
0$
b111010110000101 #
b111010110000101 '
b110000110101011 "
b110000110101011 &
#158
b1001111 %
#159
b1101011011111111 (
b11101011011111111 !
1)
b1111111101111110 #
b1111111101111110 '
b1101011110000001 "
b1101011110000001 &
#160
b1010000 %
#161
0)
b1000000111100100 !
b1000000111100100 (
b11010011001101 #
b11010011001101 '
b100110100010111 "
b100110100010111 &
#162
b1010001 %
#163
b1101001100011111 !
b1101001100011111 (
b101101010011101 #
b101101010011101 '
b111100010000010 "
b111100010000010 &
#164
b1010010 %
#165
b1101001100011001 (
b11101001100011001 !
1)
1$
b1110100100111001 #
b1110100100111001 '
b1110100111011111 "
b1110100111011111 &
#166
b1010011 %
#167
b1010011111010101 (
b1010011111010101 !
0)
b1001100111011011 #
b1001100111011011 '
b110111111001 "
b110111111001 &
#168
b1010100 %
#169
b1011110101000110 !
b1011110101000110 (
0$
b111110111011010 #
b111110111011010 '
b11111101101100 "
b11111101101100 &
#170
b1010101 %
#171
b100001011101111 !
b100001011101111 (
1$
b111011000110 #
b111011000110 '
b11010000101000 "
b11010000101000 &
#172
b1010110 %
#173
b110000111101100 !
b110000111101100 (
b10100100000000 #
b10100100000000 '
b11100011101011 "
b11100011101011 &
#174
b1010111 %
#175
b1011011111100001 !
b1011011111100001 (
0$
b111011011010000 #
b111011011010000 '
b100000100010001 "
b100000100010001 &
#176
b1011000 %
#177
b1000010011000110 !
b1000010011000110 (
1$
b11000010100100 #
b11000010100100 '
b101010000100001 "
b101010000100001 &
#178
b1011001 %
#179
b1000001110110010 (
b11000001110110010 !
1)
b1001101110010000 #
b1001101110010000 '
b1110100000100001 "
b1110100000100001 &
#180
b1011010 %
#181
b11010010000100110 !
b1010010000100110 (
0$
b1010110010010100 #
b1010110010010100 '
b1111011110010010 "
b1111011110010010 &
#182
b1011011 %
#183
b10010110011010100 !
b10110011010100 (
1$
b100111000101000 #
b100111000101000 '
b1101111010101011 "
b1101111010101011 &
#184
b1011100 %
#185
b10010001000001111 !
b10001000001111 (
0$
b1000110000101000 #
b1000110000101000 '
b1001010111100111 "
b1001010111100111 &
#186
b1011101 %
#187
b10101011011111000 !
b101011011111000 (
1$
b1001100100011111 #
b1001100100011111 '
b1011110111011000 "
b1011110111011000 &
#188
b1011110 %
#189
b11010110101011101 !
b1010110101011101 (
b1011100000000100 #
b1011100000000100 '
b1111010101011000 "
b1111010101011000 &
#190
b1011111 %
#191
b1111000101010100 (
b1111000101010100 !
0)
0$
b1010110011111011 #
b1010110011111011 '
b100010001011001 "
b100010001011001 &
#192
b1100000 %
#193
b1000010101010000 (
b11000010101010000 !
1)
1$
b1111001111101111 #
b1111001111101111 '
b1001000101100000 "
b1001000101100000 &
#194
b1100001 %
#195
b10111011110111000 !
b111011110111000 (
b1111001001101010 #
b1111001001101010 '
b1000010101001101 "
b1000010101001101 &
#196
b1100010 %
#197
0)
b1110000010100000 !
b1110000010100000 (
0$
b101101100010111 #
b101101100010111 '
b1000010110001001 "
b1000010110001001 &
#198
b1100011 %
#199
b1100110001110101 !
b1100110001110101 (
b10110110000110 #
b10110110000110 '
b1001111011101111 "
b1001111011101111 &
#200
b1100100 %
