homework/homework07/alu/alu.v
module alu (
    op,
    a,
    b,
    res
);

input [1:0] op;
input [3:0] a;
input [3:0] b;
output [3:0] res;

reg [3:0] ans;

assign res = ans;

always @(*) begin
    case (op)
        2'b00: ans = ~a;
        2'b01: ans = ~b;
        2'b10: ans = a & b;
        2'b11: ans = a | b;
        default: ans = 0;
    endcase
end
    
endmodule

homework/homework07/alu/test_alu.v
`include "alu.v"

module test (
);

reg [1:0] op;
reg [3:0] a;
reg [3:0] b;
wire [3:0] res;

alu u_alu(
    .op(op),
    .a(a),
    .b(b),
    .res(res)
);

integer i;
reg [3:0] a_r [99:0];
reg [3:0] b_r [99:0];
reg [3:0] op_r [99:0];
reg [3:0] ans_r [99:0];

initial begin
    $dumpfile("test.vcd");
    $dumpvars;
    $readmemh("a.ram", a_r);
    $readmemh("b.ram", b_r);
    $readmemh("op.ram", op_r);
    $readmemh("ans.ram", ans_r);
    for (i = 0; i < 100; i = 1 + i) begin
        a = a_r[i];
        b = b_r[i];
        op = op_r[i];
        #1;
        if (res != ans_r[i]) begin
            $display("failed at a: %x, b: %x, op: %x, ans: %x", a, b, op, res);
        end
    end
    $display("passed");
    $finish;
end
    
endmodule

homework/homework07/alu/test.vcd
$date
	Mon Oct 19 18:49:09 2020
$end
$version
	Icarus Verilog
$end
$timescale
	1s
$end
$scope module test $end
$var wire 4 ! res [3:0] $end
$var reg 4 " a [3:0] $end
$var reg 4 # b [3:0] $end
$var reg 2 $ op [1:0] $end
$var integer 32 % i [31:0] $end
$scope module u_alu $end
$var wire 4 & a [3:0] $end
$var wire 4 ' b [3:0] $end
$var wire 2 ( op [1:0] $end
$var wire 4 ) res [3:0] $end
$var reg 4 * ans [3:0] $end
$upscope $end
$upscope $end
$enddefinitions $end
#0
$dumpvars
b1110 *
b1110 )
b11 (
b10 '
b1110 &
b0 %
b11 $
b10 #
b1110 "
b1110 !
$end
#1
b0 !
b0 )
b0 *
bx $
bx (
bx #
bx '
bx "
bx &
b1 %
#2
b10 %
#3
b11 %
#4
b100 %
#5
b101 %
#6
b110 %
#7
b111 %
#8
b1000 %
#9
b1001 %
#10
b1010 %
#11
b1011 %
#12
b1100 %
#13
b1101 %
#14
b1110 %
#15
b1111 %
#16
b10000 %
#17
b10001 %
#18
b10010 %
#19
b10011 %
#20
b10100 %
#21
b10101 %
#22
b10110 %
#23
b10111 %
#24
b11000 %
#25
b11001 %
#26
b11010 %
#27
b11011 %
#28
b11100 %
#29
b11101 %
#30
b11110 %
#31
b11111 %
#32
b100000 %
#33
b100001 %
#34
b100010 %
#35
b100011 %
#36
b100100 %
#37
b100101 %
#38
b100110 %
#39
b100111 %
#40
b101000 %
#41
b101001 %
#42
b101010 %
#43
b101011 %
#44
b101100 %
#45
b101101 %
#46
b101110 %
#47
b101111 %
#48
b110000 %
#49
b110001 %
#50
b110010 %
#51
b110011 %
#52
b110100 %
#53
b110101 %
#54
b110110 %
#55
b110111 %
#56
b111000 %
#57
b111001 %
#58
b111010 %
#59
b111011 %
#60
b111100 %
#61
b111101 %
#62
b111110 %
#63
b111111 %
#64
b1000000 %
#65
b1000001 %
#66
b1000010 %
#67
b1000011 %
#68
b1000100 %
#69
b1000101 %
#70
b1000110 %
#71
b1000111 %
#72
b1001000 %
#73
b1001001 %
#74
b1001010 %
#75
b1001011 %
#76
b1001100 %
#77
b1001101 %
#78
b1001110 %
#79
b1001111 %
#80
b1010000 %
#81
b1010001 %
#82
b1010010 %
#83
b1010011 %
#84
b1010100 %
#85
b1010101 %
#86
b1010110 %
#87
b1010111 %
#88
b1011000 %
#89
b1011001 %
#90
b1011010 %
#91
b1011011 %
#92
b1011100 %
#93
b1011101 %
#94
b1011110 %
#95
b1011111 %
#96
b1100000 %
#97
b1100001 %
#98
b1100010 %
#99
b1100011 %
#100
b1100100 %
