homework/homework09/car/car.v
module car_led(clk, reset, emergency, left , right, brake, led_left, led_right);

/*
 * Assume that: (a,b,c) -> reg[0,1,2] 
 */

// the special status of led on both side
`define all_off 3'b000 
`define one_on 3'b001 
`define two_on 3'b011
`define all_on 3'b111

`define go_straight 0
`define go_left 1
`define go_right 2
`define go_straight_brake 3
`define go_left_brake 4
`define go_right_brake 5
`define go_emergency 6

input clk, reset;
input emergency;
input left, right, brake;
output [2:0] led_left, led_right;

reg [3:0] status;

wire straight;
reg [2:0] led_left_reg, led_right_reg;
reg [1:0] left_cnt, right_cnt;
reg eme_cnt;

assign straight = (left == 0) && (right == 0);
assign led_left = led_left_reg;
assign led_right = led_right_reg;


always @(posedge clk or reset) begin
    if (reset) begin
        set_led(`all_off, led_left_reg);
        set_led(`all_off, led_right_reg);
        left_cnt <= 0;
        right_cnt <= 0;
        eme_cnt <= 0;
    end
    else begin
        case (status)
            `go_straight : begin
                led_left_reg <= `all_off;
                led_right_reg <= `all_off;
                left_cnt <= 0;
                right_cnt <= 0;
                eme_cnt <= 0;
            end
            `go_left: begin
                left_cnt <= left_cnt + 1;
                right_cnt <= 0;
                eme_cnt <= 0;
                led_right_reg <= `all_off;
                if (left_cnt == 0) led_left_reg <= `all_off;
                else if (left_cnt == 1) led_left_reg <= `one_on; 
                else if (left_cnt == 2) led_left_reg <= `two_on;
                else if (left_cnt == 3) led_left_reg <= `all_on;
            end
            `go_right: begin
                led_left_reg <= `all_off;
                right_cnt <= right_cnt + 1;
                left_cnt <= 0;
                eme_cnt <= 0;
                if (right_cnt == 0) led_right_reg <= `all_off;
                else if (right_cnt == 1) led_right_reg <= `one_on; 
                else if (right_cnt == 2) led_right_reg <= `two_on;
                else if (right_cnt == 3) led_right_reg <= `all_on;
            end
            `go_straight_brake: begin
                led_left_reg <= `all_on;
                led_right_reg <= `all_on;
                left_cnt <= 0;
                right_cnt <= 0;
                eme_cnt <= 0;
            end
            `go_left_brake: begin
                led_right_reg <= `all_on;
                left_cnt <= left_cnt + 1;
                right_cnt <= 0;
                eme_cnt <= 0;
                if (left_cnt == 0) led_left_reg <= `all_off;
                else if (left_cnt == 1) led_left_reg <= `one_on; 
                else if (left_cnt == 2) led_left_reg <= `two_on;
                else if (left_cnt == 3) led_left_reg <= `all_on;
            end
            `go_right_brake: begin
                led_left_reg <= `all_on;
                right_cnt <= right_cnt + 1;
                left_cnt <= 0;
                eme_cnt <= 0;
                if (right_cnt == 0) led_right_reg <= `all_off;
                else if (right_cnt == 1) led_right_reg <= `one_on; 
                else if (right_cnt == 2) led_right_reg <= `two_on;
                else if (right_cnt == 3) led_right_reg <= `all_on;
            end 
            `go_emergency: begin
                eme_cnt <= ~eme_cnt;
                left_cnt <= 0;
                right_cnt <= 0;
                if (eme_cnt) begin
                    led_right_reg <= `all_off;
                    led_left_reg <= `all_off;
                end
                else begin
                    led_right_reg <= `all_on;
                    led_left_reg <= `all_on;
                end
            end
            default: begin
                led_right_reg <= `all_off;
                led_left_reg <= `all_off;
                left_cnt <= 0;
                right_cnt <= 0;
                eme_cnt <= 0;
            end
        endcase
    end
end

always @(posedge clk or reset) begin
    if (reset == 0) begin
        if (emergency) status = `go_emergency;
        else if (left == 0 && right == 0 && brake == 0) status = `go_straight;
        else if (left == 1 && right == 0 && brake == 0) status = `go_left;
        else if (left == 0 && right == 1 && brake == 0) status = `go_right;
        else if (left == 0 && right == 0 && brake == 1) status = `go_straight_brake;
        else if (left == 1 && right == 0 && brake == 1) status = `go_left_brake;
        else if (left == 0 && right == 1 && brake == 1) status = `go_right_brake;   
    end
end

task set_led;
input [2:0] led_pos;
output reg [2:0] led;
    begin
        // $display("led pos is %d", led_pos);
        led <= led_pos;
    end
endtask

endmodule

homework/homework09/car/car_tb.v
`include "car.v"

module test (

);


reg clk, reset;
reg emergency;
reg left, right, brake;
wire [2:0] led_left, led_right;

car_led u_car(clk, reset, emergency, left , right, brake, led_left, led_right);

always #1 clk = ~clk;

reg [3:0] data [11:0];
integer i;

initial begin
    $dumpfile("test.vcd");
    $dumpvars;
    clk = 0;
    reset =  1;
    #1 reset = 0;
    $readmemb("data.bin", data);
    for (i = 0; i < 12; i = i + 1) begin
        {emergency, left, right, brake} = data[i];
        #20;
    end
    #10 $finish;
end


endmodule

homework/homework09/car/test.vcd
$date
	Thu Nov  5 19:52:03 2020
$end
$version
	Icarus Verilog
$end
$timescale
	1s
$end
$scope module test $end
$var wire 3 ! led_right [2:0] $end
$var wire 3 " led_left [2:0] $end
$var reg 1 # brake $end
$var reg 1 $ clk $end
$var reg 1 % emergency $end
$var reg 1 & left $end
$var reg 1 ' reset $end
$var reg 1 ( right $end
$var integer 32 ) i [31:0] $end
$scope module u_car $end
$var wire 1 # brake $end
$var wire 1 $ clk $end
$var wire 1 % emergency $end
$var wire 3 * led_left [2:0] $end
$var wire 3 + led_right [2:0] $end
$var wire 1 & left $end
$var wire 1 ' reset $end
$var wire 1 ( right $end
$var wire 1 , straight $end
$var reg 1 - eme_cnt $end
$var reg 3 . led_left_reg [2:0] $end
$var reg 3 / led_right_reg [2:0] $end
$var reg 2 0 left_cnt [1:0] $end
$var reg 2 1 right_cnt [1:0] $end
$var reg 4 2 status [3:0] $end
$scope task set_led $end
$var reg 3 3 led [2:0] $end
$var reg 3 4 led_pos [2:0] $end
$upscope $end
$upscope $end
$upscope $end
$enddefinitions $end
#0
$dumpvars
b0 4
b0 3
bx 2
b0 1
b0 0
bx /
bx .
0-
x,
bx +
bx *
bx )
x(
1'
x&
x%
0$
x#
bx "
bx !
$end
#1
b0 "
b0 *
b0 .
b0 !
b0 +
b0 /
1,
b110 2
1%
0&
0(
0#
b0 )
0'
1$
#2
0$
#3
b111 "
b111 *
b111 .
b111 !
b111 +
b111 /
1-
1$
#4
0$
#5
b0 "
b0 *
b0 .
b0 !
b0 +
b0 /
0-
1$
#6
0$
#7
b111 "
b111 *
b111 .
b111 !
b111 +
b111 /
1-
1$
#8
0$
#9
b0 "
b0 *
b0 .
b0 !
b0 +
b0 /
0-
1$
#10
0$
#11
b111 "
b111 *
b111 .
b111 !
b111 +
b111 /
1-
1$
#12
0$
#13
b0 "
b0 *
b0 .
b0 !
b0 +
b0 /
0-
1$
#14
0$
#15
b111 "
b111 *
b111 .
b111 !
b111 +
b111 /
1-
1$
#16
0$
#17
b0 "
b0 *
b0 .
b0 !
b0 +
b0 /
0-
1$
#18
0$
#19
b111 "
b111 *
b111 .
b111 !
b111 +
b111 /
1-
1$
#20
0$
#21
b0 "
b0 *
b0 .
b0 !
b0 +
b0 /
0-
0,
1$
1(
b1 )
#22
0$
#23
b111 "
b111 *
b111 .
b111 !
b111 +
b111 /
1-
1$
#24
0$
#25
b0 "
b0 *
b0 .
b0 !
b0 +
b0 /
0-
1$
#26
0$
#27
b111 "
b111 *
b111 .
b111 !
b111 +
b111 /
1-
1$
#28
0$
#29
b0 "
b0 *
b0 .
b0 !
b0 +
b0 /
0-
1$
#30
0$
#31
b111 "
b111 *
b111 .
b111 !
b111 +
b111 /
1-
1$
#32
0$
#33
b0 "
b0 *
b0 .
b0 !
b0 +
b0 /
0-
1$
#34
0$
#35
b111 "
b111 *
b111 .
b111 !
b111 +
b111 /
1-
1$
#36
0$
#37
b0 "
b0 *
b0 .
b0 !
b0 +
b0 /
0-
1$
#38
0$
#39
b111 "
b111 *
b111 .
b111 !
b111 +
b111 /
1-
1$
#40
0$
#41
b0 "
b0 *
b0 .
b0 !
b0 +
b0 /
0-
1$
1&
0(
b10 )
#42
0$
#43
b111 "
b111 *
b111 .
b111 !
b111 +
b111 /
1-
1$
#44
0$
#45
b0 "
b0 *
b0 .
b0 !
b0 +
b0 /
0-
1$
#46
0$
#47
b111 "
b111 *
b111 .
b111 !
b111 +
b111 /
1-
1$
#48
0$
#49
b0 "
b0 *
b0 .
b0 !
b0 +
b0 /
0-
1$
#50
0$
#51
b111 "
b111 *
b111 .
b111 !
b111 +
b111 /
1-
1$
#52
0$
#53
b0 "
b0 *
b0 .
b0 !
b0 +
b0 /
0-
1$
#54
0$
#55
b111 "
b111 *
b111 .
b111 !
b111 +
b111 /
1-
1$
#56
0$
#57
b0 "
b0 *
b0 .
b0 !
b0 +
b0 /
0-
1$
#58
0$
#59
b111 "
b111 *
b111 .
b111 !
b111 +
b111 /
1-
1$
#60
0$
#61
b0 "
b0 *
b0 .
b0 !
b0 +
b0 /
0-
1,
1$
0&
1#
b11 )
#62
0$
#63
b111 "
b111 *
b111 .
b111 !
b111 +
b111 /
1-
1$
#64
0$
#65
b0 "
b0 *
b0 .
b0 !
b0 +
b0 /
0-
1$
#66
0$
#67
b111 "
b111 *
b111 .
b111 !
b111 +
b111 /
1-
1$
#68
0$
#69
b0 "
b0 *
b0 .
b0 !
b0 +
b0 /
0-
1$
#70
0$
#71
b111 "
b111 *
b111 .
b111 !
b111 +
b111 /
1-
1$
#72
0$
#73
b0 "
b0 *
b0 .
b0 !
b0 +
b0 /
0-
1$
#74
0$
#75
b111 "
b111 *
b111 .
b111 !
b111 +
b111 /
1-
1$
#76
0$
#77
b0 "
b0 *
b0 .
b0 !
b0 +
b0 /
0-
1$
#78
0$
#79
b111 "
b111 *
b111 .
b111 !
b111 +
b111 /
1-
1$
#80
0$
#81
b0 "
b0 *
b0 .
b0 !
b0 +
b0 /
0-
0,
1$
1(
b100 )
#82
0$
#83
b111 "
b111 *
b111 .
b111 !
b111 +
b111 /
1-
1$
#84
0$
#85
b0 "
b0 *
b0 .
b0 !
b0 +
b0 /
0-
1$
#86
0$
#87
b111 "
b111 *
b111 .
b111 !
b111 +
b111 /
1-
1$
#88
0$
#89
b0 "
b0 *
b0 .
b0 !
b0 +
b0 /
0-
1$
#90
0$
#91
b111 "
b111 *
b111 .
b111 !
b111 +
b111 /
1-
1$
#92
0$
#93
b0 "
b0 *
b0 .
b0 !
b0 +
b0 /
0-
1$
#94
0$
#95
b111 "
b111 *
b111 .
b111 !
b111 +
b111 /
1-
1$
#96
0$
#97
b0 "
b0 *
b0 .
b0 !
b0 +
b0 /
0-
1$
#98
0$
#99
b111 "
b111 *
b111 .
b111 !
b111 +
b111 /
1-
1$
#100
0$
#101
b0 "
b0 *
b0 .
b0 !
b0 +
b0 /
0-
1$
1&
0(
b101 )
#102
0$
#103
b111 "
b111 *
b111 .
b111 !
b111 +
b111 /
1-
1$
#104
0$
#105
b0 "
b0 *
b0 .
b0 !
b0 +
b0 /
0-
1$
#106
0$
#107
b111 "
b111 *
b111 .
b111 !
b111 +
b111 /
1-
1$
#108
0$
#109
b0 "
b0 *
b0 .
b0 !
b0 +
b0 /
0-
1$
#110
0$
#111
b111 "
b111 *
b111 .
b111 !
b111 +
b111 /
1-
1$
#112
0$
#113
b0 "
b0 *
b0 .
b0 !
b0 +
b0 /
0-
1$
#114
0$
#115
b111 "
b111 *
b111 .
b111 !
b111 +
b111 /
1-
1$
#116
0$
#117
b0 "
b0 *
b0 .
b0 !
b0 +
b0 /
0-
1$
#118
0$
#119
b111 "
b111 *
b111 .
b111 !
b111 +
b111 /
1-
1$
#120
0$
#121
b0 "
b0 *
b0 .
b0 !
b0 +
b0 /
0-
b0 2
1,
1$
0%
0&
0#
b110 )
#122
0$
#123
1$
#124
0$
#125
1$
#126
0$
#127
1$
#128
0$
#129
1$
#130
0$
#131
1$
#132
0$
#133
1$
#134
0$
#135
1$
#136
0$
#137
1$
#138
0$
#139
1$
#140
0$
#141
b11 2
1$
1#
b111 )
#142
0$
#143
b111 !
b111 +
b111 /
b111 "
b111 *
b111 .
1$
#144
0$
#145
1$
#146
0$
#147
1$
#148
0$
#149
1$
#150
0$
#151
1$
#152
0$
#153
1$
#154
0$
#155
1$
#156
0$
#157
1$
#158
0$
#159
1$
#160
0$
#161
b10 2
0,
1$
1(
0#
b1000 )
#162
0$
#163
b0 !
b0 +
b0 /
b1 1
b0 "
b0 *
b0 .
1$
#164
0$
#165
b1 !
b1 +
b1 /
b10 1
1$
#166
0$
#167
b11 !
b11 +
b11 /
b11 1
1$
#168
0$
#169
b111 !
b111 +
b111 /
b0 1
1$
#170
0$
#171
b0 !
b0 +
b0 /
b1 1
1$
#172
0$
#173
b1 !
b1 +
b1 /
b10 1
1$
#174
0$
#175
b11 !
b11 +
b11 /
b11 1
1$
#176
0$
#177
b111 !
b111 +
b111 /
b0 1
1$
#178
0$
#179
b0 !
b0 +
b0 /
b1 1
1$
#180
0$
#181
b1 !
b1 +
b1 /
b10 1
b1 2
1$
1&
0(
b1001 )
#182
0$
#183
b0 !
b0 +
b0 /
b0 1
b1 0
1$
#184
0$
#185
b1 "
b1 *
b1 .
b10 0
1$
#186
0$
#187
b11 "
b11 *
b11 .
b11 0
1$
#188
0$
#189
b111 "
b111 *
b111 .
b0 0
1$
#190
0$
#191
b0 "
b0 *
b0 .
b1 0
1$
#192
0$
#193
b1 "
b1 *
b1 .
b10 0
1$
#194
0$
#195
b11 "
b11 *
b11 .
b11 0
1$
#196
0$
#197
b111 "
b111 *
b111 .
b0 0
1$
#198
0$
#199
b0 "
b0 *
b0 .
b1 0
1$
#200
0$
#201
b1 "
b1 *
b1 .
b10 0
b101 2
1$
0&
1(
1#
b1010 )
#202
0$
#203
b0 0
b1 1
b111 "
b111 *
b111 .
1$
#204
0$
#205
b1 !
b1 +
b1 /
b10 1
1$
#206
0$
#207
b11 !
b11 +
b11 /
b11 1
1$
#208
0$
#209
b111 !
b111 +
b111 /
b0 1
1$
#210
0$
#211
b0 !
b0 +
b0 /
b1 1
1$
#212
0$
#213
b1 !
b1 +
b1 /
b10 1
1$
#214
0$
#215
b11 !
b11 +
b11 /
b11 1
1$
#216
0$
#217
b111 !
b111 +
b111 /
b0 1
1$
#218
0$
#219
b0 !
b0 +
b0 /
b1 1
1$
#220
0$
#221
b1 !
b1 +
b1 /
b10 1
b100 2
1$
1&
0(
b1011 )
#222
0$
#223
b0 "
b0 *
b0 .
b0 1
b1 0
b111 !
b111 +
b111 /
1$
#224
0$
#225
b1 "
b1 *
b1 .
b10 0
1$
#226
0$
#227
b11 "
b11 *
b11 .
b11 0
1$
#228
0$
#229
b111 "
b111 *
b111 .
b0 0
1$
#230
0$
#231
b0 "
b0 *
b0 .
b1 0
1$
#232
0$
#233
b1 "
b1 *
b1 .
b10 0
1$
#234
0$
#235
b11 "
b11 *
b11 .
b11 0
1$
#236
0$
#237
b111 "
b111 *
b111 .
b0 0
1$
#238
0$
#239
b0 "
b0 *
b0 .
b1 0
1$
#240
0$
#241
b1 "
b1 *
b1 .
b10 0
1$
b1100 )
#242
0$
#243
b11 "
b11 *
b11 .
b11 0
1$
#244
0$
#245
b111 "
b111 *
b111 .
b0 0
1$
#246
0$
#247
b0 "
b0 *
b0 .
b1 0
1$
#248
0$
#249
b1 "
b1 *
b1 .
b10 0
1$
#250
0$
#251
b11 "
b11 *
b11 .
b11 0
1$
