homework/homework09/car/car.v
module car_led(clk, reset, emergency, left , right, brake, led_left, led_right);

/*
 * Assume that: (a,b,c) -> reg[0,1,2] 
 */

// the special status of led on both side
`define all_off 3'b000 
`define one_on 3'b001 
`define two_on 3'b011
`define all_on 3'b111

`define go_straight 0
`define go_left 1
`define go_right 2
`define go_straight_brake 3
`define go_left_brake 4
`define go_right_brake 5
`define go_emergency 6

input clk, reset;
input emergency;
input left, right, brake;
output [2:0] led_left, led_right;

reg [3:0] status;

wire straight;
reg [2:0] led_left_reg, led_right_reg;
reg [1:0] left_cnt, right_cnt;
reg eme_cnt;

assign straight = (left == 0) && (right == 0);
assign led_left = led_left_reg;
assign led_right = led_right_reg;


always @(posedge clk or reset) begin
    if (reset) begin
        set_led(`all_off, led_left_reg);
        set_led(`all_off, led_right_reg);
        left_cnt <= 0;
        right_cnt <= 0;
        eme_cnt <= 0;
    end
    else begin
        case (status)
            `go_straight : begin
                led_left_reg <= `all_off;
                led_right_reg <= `all_off;
                left_cnt <= 0;
                right_cnt <= 0;
                eme_cnt <= 0;
            end
            `go_left: begin
                left_cnt <= left_cnt + 1;
                right_cnt <= 0;
                eme_cnt <= 0;
                led_right_reg <= `all_off;
                if (left_cnt == 0) led_left_reg <= `all_off;
                else if (left_cnt == 1) led_left_reg <= `one_on; 
                else if (left_cnt == 2) led_left_reg <= `two_on;
                else if (left_cnt == 3) led_left_reg <= `all_on;
            end
            `go_right: begin
                led_left_reg <= `all_off;
                right_cnt <= right_cnt + 1;
                left_cnt <= 0;
                eme_cnt <= 0;
                if (right_cnt == 0) led_right_reg <= `all_off;
                else if (right_cnt == 1) led_right_reg <= `one_on; 
                else if (right_cnt == 2) led_right_reg <= `two_on;
                else if (right_cnt == 3) led_right_reg <= `all_on;
            end
            `go_straight_brake: begin
                led_left_reg <= `all_on;
                led_right_reg <= `all_on;
                left_cnt <= 0;
                right_cnt <= 0;
                eme_cnt <= 0;
            end
            `go_left_brake: begin
                led_right_reg <= `all_on;
                left_cnt <= left_cnt + 1;
                right_cnt <= 0;
                eme_cnt <= 0;
                if (left_cnt == 0) led_left_reg <= `all_off;
                else if (left_cnt == 1) led_left_reg <= `one_on; 
                else if (left_cnt == 2) led_left_reg <= `two_on;
                else if (left_cnt == 3) led_left_reg <= `all_on;
            end
            `go_right_brake: begin
                led_left_reg <= `all_on;
                right_cnt <= right_cnt + 1;
                left_cnt <= 0;
                eme_cnt <= 0;
                if (right_cnt == 0) led_right_reg <= `all_off;
                else if (right_cnt == 1) led_right_reg <= `one_on; 
                else if (right_cnt == 2) led_right_reg <= `two_on;
                else if (right_cnt == 3) led_right_reg <= `all_on;
            end 
            `go_emergency: begin
                eme_cnt <= ~eme_cnt;
                left_cnt <= 0;
                right_cnt <= 0;
                if (eme_cnt) begin
                    led_right_reg <= `all_off;
                    led_left_reg <= `all_off;
                end
                else begin
                    led_right_reg <= `all_on;
                    led_left_reg <= `all_on;
                end
            end
            default: begin
                led_right_reg <= `all_off;
                led_left_reg <= `all_off;
                left_cnt <= 0;
                right_cnt <= 0;
                eme_cnt <= 0;
            end
        endcase
    end
end

always @(posedge clk or reset) begin
    if (reset == 0) begin
        if (emergency) status = `go_emergency;
        else if (left == 0 && right == 0 && brake == 0) status = `go_straight;
        else if (left == 1 && right == 0 && brake == 0) status = `go_left;
        else if (left == 0 && right == 1 && brake == 0) status = `go_right;
        else if (left == 0 && right == 0 && brake == 1) status = `go_straight_brake;
        else if (left == 1 && right == 0 && brake == 1) status = `go_left_brake;
        else if (left == 0 && right == 1 && brake == 1) status = `go_right_brake;   
    end
end

task set_led;
input [2:0] led_pos;
output reg [2:0] led;
    begin
        // $display("led pos is %d", led_pos);
        led <= led_pos;
    end
endtask

endmodule

homework/homework09/car/car_tb.v
`include "car.v"
`timescale 1ns/1ns

module test (

);


reg clk, reset;
reg emergency;
reg left, right, brake;
wire [2:0] led_left, led_right;

car_led u_car(clk, reset, emergency, left , right, brake, led_left, led_right);

always #5 clk = ~clk;

reg [3:0] data [11:0];
integer i;

initial begin
    $dumpfile("test.vcd");
    $dumpvars;
    clk = 0;
    reset =  1;
    #1 reset = 0;
    $readmemb("data.bin", data);
    for (i = 0; i < 12; i = i + 1) begin
        {emergency, left, right, brake} = data[i];
        #20;
    end
    #10 $finish;
end


endmodule

homework/homework09/car/test.vcd
$date
	Fri Nov  6 16:55:03 2020
$end
$version
	Icarus Verilog
$end
$timescale
	1ns
$end
$scope module test $end
$var wire 3 ! led_right [2:0] $end
$var wire 3 " led_left [2:0] $end
$var reg 1 # brake $end
$var reg 1 $ clk $end
$var reg 1 % emergency $end
$var reg 1 & left $end
$var reg 1 ' reset $end
$var reg 1 ( right $end
$var integer 32 ) i [31:0] $end
$scope module u_car $end
$var wire 1 # brake $end
$var wire 1 $ clk $end
$var wire 1 % emergency $end
$var wire 3 * led_left [2:0] $end
$var wire 3 + led_right [2:0] $end
$var wire 1 & left $end
$var wire 1 ' reset $end
$var wire 1 ( right $end
$var wire 1 , straight $end
$var reg 1 - eme_cnt $end
$var reg 3 . led_left_reg [2:0] $end
$var reg 3 / led_right_reg [2:0] $end
$var reg 2 0 left_cnt [1:0] $end
$var reg 2 1 right_cnt [1:0] $end
$var reg 4 2 status [3:0] $end
$scope task set_led $end
$var reg 3 3 led [2:0] $end
$var reg 3 4 led_pos [2:0] $end
$upscope $end
$upscope $end
$upscope $end
$enddefinitions $end
#0
$dumpvars
b0 4
b0 3
bx 2
b0 1
b0 0
bx /
bx .
0-
x,
bx +
bx *
bx )
x(
1'
x&
x%
0$
x#
bx "
bx !
$end
#1
b0 "
b0 *
b0 .
b0 !
b0 +
b0 /
1,
b110 2
1%
0&
0(
0#
b0 )
0'
#5
b111 "
b111 *
b111 .
b111 !
b111 +
b111 /
1-
1$
#10
0$
#15
b0 "
b0 *
b0 .
b0 !
b0 +
b0 /
0-
1$
#20
0$
#21
0,
1(
b1 )
#25
b111 "
b111 *
b111 .
b111 !
b111 +
b111 /
1-
1$
#30
0$
#35
b0 "
b0 *
b0 .
b0 !
b0 +
b0 /
0-
1$
#40
0$
#41
1&
0(
b10 )
#45
b111 "
b111 *
b111 .
b111 !
b111 +
b111 /
1-
1$
#50
0$
#55
b0 "
b0 *
b0 .
b0 !
b0 +
b0 /
0-
1$
#60
0$
#61
1,
0&
1#
b11 )
#65
b111 "
b111 *
b111 .
b111 !
b111 +
b111 /
1-
1$
#70
0$
#75
b0 "
b0 *
b0 .
b0 !
b0 +
b0 /
0-
1$
#80
0$
#81
0,
1(
b100 )
#85
b111 "
b111 *
b111 .
b111 !
b111 +
b111 /
1-
1$
#90
0$
#95
b0 "
b0 *
b0 .
b0 !
b0 +
b0 /
0-
1$
#100
0$
#101
1&
0(
b101 )
#105
b111 "
b111 *
b111 .
b111 !
b111 +
b111 /
1-
1$
#110
0$
#115
b0 "
b0 *
b0 .
b0 !
b0 +
b0 /
0-
1$
#120
0$
#121
1,
0%
0&
0#
b110 )
#125
b0 2
1$
#130
0$
#135
1$
#140
0$
#141
1#
b111 )
#145
b111 !
b111 +
b111 /
b111 "
b111 *
b111 .
b11 2
1$
#150
0$
#155
1$
#160
0$
#161
0,
1(
0#
b1000 )
#165
b0 !
b0 +
b0 /
b1 1
b0 "
b0 *
b0 .
b10 2
1$
#170
0$
#175
b1 !
b1 +
b1 /
b10 1
1$
#180
0$
#181
1&
0(
b1001 )
#185
b0 !
b0 +
b0 /
b0 1
b1 0
b1 2
1$
#190
0$
#195
b1 "
b1 *
b1 .
b10 0
1$
#200
0$
#201
0&
1(
1#
b1010 )
#205
b0 0
b1 1
b111 "
b111 *
b111 .
b101 2
1$
#210
0$
#215
b1 !
b1 +
b1 /
b10 1
1$
#220
0$
#221
1&
0(
b1011 )
#225
b0 "
b0 *
b0 .
b0 1
b1 0
b111 !
b111 +
b111 /
b100 2
1$
#230
0$
#235
b1 "
b1 *
b1 .
b10 0
1$
#240
0$
#241
b1100 )
#245
b11 "
b11 *
b11 .
b11 0
1$
