homework/homework03/byteInv/byteInv.v
module byteInv (
    in, 
    out
);

input [31:0] in;
output [31:0] out;

assign out = {in[7:0], in[15:8], in[23:16], in[31:24]};
    
endmodule

homework/homework03/task-1-2-byteInv/test_byteInv.v
`include "byteInv.v"

module test (

);

reg [31:0] a;
wire [31:0] b;

byteInv u_byte(
    .in(a),
    .out(b)
);

reg [31:0] in_test [99:0];
reg [31:0] out_test [99:0];

integer i;

initial begin
    $dumpfile("test_byte.vcd");
    $dumpvars;
    $readmemh("byteInv.in", in_test);
    $readmemh("byteInv.out", out_test);
    for (i = 0; i < 100; i = 1 + i) begin
        a = in_test[i];
        #1;
        if (b !== out_test[i]) begin
            $display("test failed at %d! in: %08x, out: %08x, should: %08x", i, a, b, out_test[i]);
            // $finish;
        end
    end
    #1;
    $display("test passed");
    $finish;
end

endmodule

homework/homework03/task-1-2-byteInv/test_byte.vcd
$date
	Mon Sep 28 21:46:35 2020
$end
$version
	Icarus Verilog
$end
$timescale
	1s
$end
$scope module test $end
$var wire 32 ! b [31:0] $end
$var reg 32 " a [31:0] $end
$var integer 32 # i [31:0] $end
$scope module u_byte $end
$var wire 32 $ in [31:0] $end
$var wire 32 % out [31:0] $end
$upscope $end
$upscope $end
$enddefinitions $end
#0
$dumpvars
bx %
bx $
b0 #
bx "
bx !
$end
#1
b1 #
#2
b10 #
#3
b11 #
#4
b100 #
#5
b101 #
#6
b110 #
#7
b111 #
#8
b1000 #
#9
b1001 #
#10
b1010 #
#11
b1011 #
#12
b1100 #
#13
b1101 #
#14
b1110 #
#15
b1111 #
#16
b10000 #
#17
b10001 #
#18
b10010 #
#19
b10011 #
#20
b10100 #
#21
b10101 #
#22
b10110 #
#23
b10111 #
#24
b11000 #
#25
b11001 #
#26
b11010 #
#27
b11011 #
#28
b11100 #
#29
b11101 #
#30
b11110 #
#31
b11111 #
#32
b100000 #
#33
b100001 #
#34
b100010 #
#35
b100011 #
#36
b100100 #
#37
b100101 #
#38
b100110 #
#39
b100111 #
#40
b101000 #
#41
b101001 #
#42
b101010 #
#43
b101011 #
#44
b101100 #
#45
b101101 #
#46
b101110 #
#47
b101111 #
#48
b110000 #
#49
b110001 #
#50
b110010 #
#51
b110011 #
#52
b110100 #
#53
b110101 #
#54
b110110 #
#55
b110111 #
#56
b111000 #
#57
b111001 #
#58
b111010 #
#59
b111011 #
#60
b111100 #
#61
b111101 #
#62
b111110 #
#63
b111111 #
#64
b1000000 #
#65
b1000001 #
#66
b1000010 #
#67
b1000011 #
#68
b1000100 #
#69
b1000101 #
#70
b1000110 #
#71
b1000111 #
#72
b1001000 #
#73
b1001001 #
#74
b1001010 #
#75
b1001011 #
#76
b1001100 #
#77
b1001101 #
#78
b1001110 #
#79
b1001111 #
#80
b1010000 #
#81
b1010001 #
#82
b1010010 #
#83
b1010011 #
#84
b1010100 #
#85
b1010101 #
#86
b1010110 #
#87
b1010111 #
#88
b1011000 #
#89
b1011001 #
#90
b1011010 #
#91
b1011011 #
#92
b1011100 #
#93
b1011101 #
#94
b1011110 #
#95
b1011111 #
#96
b1100000 #
#97
b1100001 #
#98
b1100010 #
#99
b1100011 #
#100
b1100100 #
