homework/homework09/light/light_no.v
module traffic_light(clk, reset, light_ew_rgyl, light_sn_rgyl); 

input clk;
input reset;
output [3:0] light_ew_rgyl;
output [3:0] light_sn_rgyl;

`define idle 0
`define pre 11 
`define ew_green 1
`define ew_yellow 2
`define ew_left 3
`define ew_yellow_next 4
`define ew_red 5
`define sn_green 6
`define sn_yellow 7
`define sn_left 8
`define sn_yellow_next 9
`define sn_red 10

reg [3:0] status;

assign light_ew_rgyl[0] = (status == `ew_left);
assign light_ew_rgyl[1] = (status == `ew_yellow || status == `ew_yellow_next);
assign light_ew_rgyl[2] = (status == `ew_green);
assign light_ew_rgyl[3] = (status != `ew_green) && (status != `ew_yellow) && (status != `ew_yellow_next) && (status != `ew_left);
assign light_sn_rgyl[0] = (status == `sn_left);
assign light_sn_rgyl[1] = (status == `sn_yellow || status == `sn_yellow_next);
assign light_sn_rgyl[2] = (status == `sn_green);
assign light_sn_rgyl[3] = (status != `sn_green) && (status != `sn_yellow) && (status != `sn_yellow_next) && (status != `sn_left);

reg [7:0] cnt;

always @(posedge clk or posedge reset) begin
    if (reset) begin
        status <= `idle;
        cnt <= 0;
    end
    else begin
        case (status)
            // `idle: wait_and_change(3, `sn_green, status); 
            `idle: begin
                if (cnt + 1 == 3) begin
                    cnt <= 0;
                    status <= `sn_green;
                end
                else cnt <= cnt + 1;
            end
            // `sn_green: wait_and_change(30, `sn_yellow, status);
            `sn_green: begin
                if (cnt + 1 == 30) begin
                    cnt <= 0;
                    status <= `sn_yellow;
                end
                else cnt <= cnt + 1;
            end
            // `sn_yellow: wait_and_change(5, `sn_left, status);
            `sn_yellow: begin
                if (cnt + 1 == 5) begin
                    cnt <= 0;
                    status <= `sn_left;
                end
                else cnt <= cnt + 1;
            end
            // `sn_left: wait_and_change(15, `sn_yellow_next, status);
            `sn_left: begin
                if (cnt + 1 == 15) begin
                    cnt <= 0;
                    status <= `sn_yellow_next;
                end
                else cnt <= cnt + 1;
            end 
            // `sn_yellow_next: wait_and_change(5, `sn_red, status);
            `sn_yellow_next: begin
                if (cnt + 1 == 5) begin
                    cnt <= 0;
                    status <= `sn_red;
                end
                else cnt <= cnt + 1;
            end
            // `sn_red: wait_and_change(3, `ew_green, status);
            `sn_red: begin
                if (cnt + 1 == 3) begin
                    cnt <= 0;
                    status <= `ew_green;
                end
                else cnt <= cnt + 1;
            end
            // `ew_green: wait_and_change(40, `ew_yellow, status);
            `ew_green: begin
                if (cnt + 1 == 40) begin
                    cnt <= 0;
                    status <= `ew_yellow;
                end
                else cnt <= cnt + 1;
            end
            // `ew_yellow: wait_and_change(5, `ew_left, status);
            `ew_yellow: begin
                if (cnt + 1 == 5) begin
                    cnt <= 0;
                    status <= `ew_left;
                end
                else cnt <= cnt + 1;
            end
            // `ew_left: wait_and_change(15, `ew_yellow_next, status);
            `ew_left: begin
                if (cnt + 1 == 15) begin
                    cnt <= 0;
                    status <= `ew_yellow_next;
                end
                else cnt <= cnt + 1;
            end
            // `ew_yellow_next: wait_and_change(5, `ew_red, status);
            `ew_yellow_next: begin
                if (cnt + 1 == 5) begin
                    cnt <= 0;
                    status <= `ew_red;
                end
                else cnt <= cnt + 1;
            end
            // `ew_red: wait_and_change(2, `sn_green, status);
            `ew_red: begin
                if (cnt + 1 == 2) begin
                    cnt <= 0;
                    status <= `sn_green;
                end
                else cnt <= cnt + 1;
            end
            default: status <= `idle;
        endcase
    end
end


endmodule

homework/homework09/light/light_no_tb.v
`include "light_no.v"
`timescale 1ns/1ns
module test (

);

reg clk, reset;
wire  [3:0] light_ew_rgyl;
wire [3:0] light_sn_rgyl;

traffic_light u(
    clk, reset, light_ew_rgyl, light_sn_rgyl
);

always #5 clk = ~clk;

integer i;
reg [3:0] sta;
reg [7:0] cnt;

initial begin
    $dumpfile("test.vcd");
    $dumpvars;
    clk = 0;
    #1 reset = 1;
    #1 reset = 0;
    sta = u.status;
    cnt = 0;
    for (i = 0; i < 20; i = i) begin
        @(posedge clk) begin
            cnt = cnt + 1; 
        end
        if (u.status != sta) begin
            $display("state: %d, last: %d", sta, cnt); 
            sta = u.status;
            cnt = 0;
            i = i + 1;
        end
    end    
    #20;
    $finish;
end

endmodule

homework/homework09/light/test.vcd
$date
	Sat Nov 28 11:49:58 2020
$end
$version
	Icarus Verilog
$end
$timescale
	1ns
$end
$scope module test $end
$var wire 4 ! light_sn_rgyl [3:0] $end
$var wire 4 " light_ew_rgyl [3:0] $end
$var reg 1 # clk $end
$var reg 8 $ cnt [7:0] $end
$var reg 1 % reset $end
$var reg 4 & sta [3:0] $end
$var integer 32 ' i [31:0] $end
$scope module u $end
$var wire 1 # clk $end
$var wire 1 % reset $end
$var wire 4 ( light_sn_rgyl [3:0] $end
$var wire 4 ) light_ew_rgyl [3:0] $end
$var reg 8 * cnt [7:0] $end
$var reg 4 + status [3:0] $end
$upscope $end
$upscope $end
$enddefinitions $end
#0
$dumpvars
bx +
bx *
bx )
bx (
bx '
bx &
x%
bx $
0#
bx "
bx !
$end
#1
b0 *
b1000 "
b1000 )
b1000 !
b1000 (
b0 +
1%
#2
b0 '
b0 $
b0 &
0%
#5
b1 *
b1 $
1#
#10
0#
#15
b10 *
b10 $
1#
#20
0#
#25
b100 !
b100 (
b110 +
b0 *
b11 $
1#
#30
0#
#35
b1 *
b1 '
b110 &
b0 $
1#
#40
0#
#45
b10 *
b1 $
1#
#50
0#
#55
b11 *
b10 $
1#
#60
0#
#65
b100 *
b11 $
1#
#70
0#
#75
b101 *
b100 $
1#
#80
0#
#85
b110 *
b101 $
1#
#90
0#
#95
b111 *
b110 $
1#
#100
0#
#105
b1000 *
b111 $
1#
#110
0#
#115
b1001 *
b1000 $
1#
#120
0#
#125
b1010 *
b1001 $
1#
#130
0#
#135
b1011 *
b1010 $
1#
#140
0#
#145
b1100 *
b1011 $
1#
#150
0#
#155
b1101 *
b1100 $
1#
#160
0#
#165
b1110 *
b1101 $
1#
#170
0#
#175
b1111 *
b1110 $
1#
#180
0#
#185
b10000 *
b1111 $
1#
#190
0#
#195
b10001 *
b10000 $
1#
#200
0#
#205
b10010 *
b10001 $
1#
#210
0#
#215
b10011 *
b10010 $
1#
#220
0#
#225
b10100 *
b10011 $
1#
#230
0#
#235
b10101 *
b10100 $
1#
#240
0#
#245
b10110 *
b10101 $
1#
#250
0#
#255
b10111 *
b10110 $
1#
#260
0#
#265
b11000 *
b10111 $
1#
#270
0#
#275
b11001 *
b11000 $
1#
#280
0#
#285
b11010 *
b11001 $
1#
#290
0#
#295
b11011 *
b11010 $
1#
#300
0#
#305
b11100 *
b11011 $
1#
#310
0#
#315
b11101 *
b11100 $
1#
#320
0#
#325
b10 !
b10 (
b111 +
b0 *
b11101 $
1#
#330
0#
#335
b1 *
b10 '
b111 &
b0 $
1#
#340
0#
#345
b10 *
b1 $
1#
#350
0#
#355
b11 *
b10 $
1#
#360
0#
#365
b100 *
b11 $
1#
#370
0#
#375
b1 !
b1 (
b1000 +
b0 *
b100 $
1#
#380
0#
#385
b1 *
b11 '
b1000 &
b0 $
1#
#390
0#
#395
b10 *
b1 $
1#
#400
0#
#405
b11 *
b10 $
1#
#410
0#
#415
b100 *
b11 $
1#
#420
0#
#425
b101 *
b100 $
1#
#430
0#
#435
b110 *
b101 $
1#
#440
0#
#445
b111 *
b110 $
1#
#450
0#
#455
b1000 *
b111 $
1#
#460
0#
#465
b1001 *
b1000 $
1#
#470
0#
#475
b1010 *
b1001 $
1#
#480
0#
#485
b1011 *
b1010 $
1#
#490
0#
#495
b1100 *
b1011 $
1#
#500
0#
#505
b1101 *
b1100 $
1#
#510
0#
#515
b1110 *
b1101 $
1#
#520
0#
#525
b10 !
b10 (
b1001 +
b0 *
b1110 $
1#
#530
0#
#535
b1 *
b100 '
b1001 &
b0 $
1#
#540
0#
#545
b10 *
b1 $
1#
#550
0#
#555
b11 *
b10 $
1#
#560
0#
#565
b100 *
b11 $
1#
#570
0#
#575
b1000 !
b1000 (
b1010 +
b0 *
b100 $
1#
#580
0#
#585
b1 *
b101 '
b1010 &
b0 $
1#
#590
0#
#595
b10 *
b1 $
1#
#600
0#
#605
b100 "
b100 )
b1 +
b0 *
b10 $
1#
#610
0#
#615
b1 *
b110 '
b1 &
b0 $
1#
#620
0#
#625
b10 *
b1 $
1#
#630
0#
#635
b11 *
b10 $
1#
#640
0#
#645
b100 *
b11 $
1#
#650
0#
#655
b101 *
b100 $
1#
#660
0#
#665
b110 *
b101 $
1#
#670
0#
#675
b111 *
b110 $
1#
#680
0#
#685
b1000 *
b111 $
1#
#690
0#
#695
b1001 *
b1000 $
1#
#700
0#
#705
b1010 *
b1001 $
1#
#710
0#
#715
b1011 *
b1010 $
1#
#720
0#
#725
b1100 *
b1011 $
1#
#730
0#
#735
b1101 *
b1100 $
1#
#740
0#
#745
b1110 *
b1101 $
1#
#750
0#
#755
b1111 *
b1110 $
1#
#760
0#
#765
b10000 *
b1111 $
1#
#770
0#
#775
b10001 *
b10000 $
1#
#780
0#
#785
b10010 *
b10001 $
1#
#790
0#
#795
b10011 *
b10010 $
1#
#800
0#
#805
b10100 *
b10011 $
1#
#810
0#
#815
b10101 *
b10100 $
1#
#820
0#
#825
b10110 *
b10101 $
1#
#830
0#
#835
b10111 *
b10110 $
1#
#840
0#
#845
b11000 *
b10111 $
1#
#850
0#
#855
b11001 *
b11000 $
1#
#860
0#
#865
b11010 *
b11001 $
1#
#870
0#
#875
b11011 *
b11010 $
1#
#880
0#
#885
b11100 *
b11011 $
1#
#890
0#
#895
b11101 *
b11100 $
1#
#900
0#
#905
b11110 *
b11101 $
1#
#910
0#
#915
b11111 *
b11110 $
1#
#920
0#
#925
b100000 *
b11111 $
1#
#930
0#
#935
b100001 *
b100000 $
1#
#940
0#
#945
b100010 *
b100001 $
1#
#950
0#
#955
b100011 *
b100010 $
1#
#960
0#
#965
b100100 *
b100011 $
1#
#970
0#
#975
b100101 *
b100100 $
1#
#980
0#
#985
b100110 *
b100101 $
1#
#990
0#
#995
b100111 *
b100110 $
1#
#1000
0#
#1005
b10 "
b10 )
b10 +
b0 *
b100111 $
1#
#1010
0#
#1015
b1 *
b111 '
b10 &
b0 $
1#
#1020
0#
#1025
b10 *
b1 $
1#
#1030
0#
#1035
b11 *
b10 $
1#
#1040
0#
#1045
b100 *
b11 $
1#
#1050
0#
#1055
b1 "
b1 )
b11 +
b0 *
b100 $
1#
#1060
0#
#1065
b1 *
b1000 '
b11 &
b0 $
1#
#1070
0#
#1075
b10 *
b1 $
1#
#1080
0#
#1085
b11 *
b10 $
1#
#1090
0#
#1095
b100 *
b11 $
1#
#1100
0#
#1105
b101 *
b100 $
1#
#1110
0#
#1115
b110 *
b101 $
1#
#1120
0#
#1125
b111 *
b110 $
1#
#1130
0#
#1135
b1000 *
b111 $
1#
#1140
0#
#1145
b1001 *
b1000 $
1#
#1150
0#
#1155
b1010 *
b1001 $
1#
#1160
0#
#1165
b1011 *
b1010 $
1#
#1170
0#
#1175
b1100 *
b1011 $
1#
#1180
0#
#1185
b1101 *
b1100 $
1#
#1190
0#
#1195
b1110 *
b1101 $
1#
#1200
0#
#1205
b10 "
b10 )
b100 +
b0 *
b1110 $
1#
#1210
0#
#1215
b1 *
b1001 '
b100 &
b0 $
1#
#1220
0#
#1225
b10 *
b1 $
1#
#1230
0#
#1235
b11 *
b10 $
1#
#1240
0#
#1245
b100 *
b11 $
1#
#1250
0#
#1255
b1000 "
b1000 )
b101 +
b0 *
b100 $
1#
#1260
0#
#1265
b1 *
b1010 '
b101 &
b0 $
1#
#1270
0#
#1275
b100 !
b100 (
b110 +
b0 *
b1 $
1#
#1280
0#
#1285
b1 *
b1011 '
b110 &
b0 $
1#
#1290
0#
#1295
b10 *
b1 $
1#
#1300
0#
#1305
b11 *
b10 $
1#
#1310
0#
#1315
b100 *
b11 $
1#
#1320
0#
#1325
b101 *
b100 $
1#
#1330
0#
#1335
b110 *
b101 $
1#
#1340
0#
#1345
b111 *
b110 $
1#
#1350
0#
#1355
b1000 *
b111 $
1#
#1360
0#
#1365
b1001 *
b1000 $
1#
#1370
0#
#1375
b1010 *
b1001 $
1#
#1380
0#
#1385
b1011 *
b1010 $
1#
#1390
0#
#1395
b1100 *
b1011 $
1#
#1400
0#
#1405
b1101 *
b1100 $
1#
#1410
0#
#1415
b1110 *
b1101 $
1#
#1420
0#
#1425
b1111 *
b1110 $
1#
#1430
0#
#1435
b10000 *
b1111 $
1#
#1440
0#
#1445
b10001 *
b10000 $
1#
#1450
0#
#1455
b10010 *
b10001 $
1#
#1460
0#
#1465
b10011 *
b10010 $
1#
#1470
0#
#1475
b10100 *
b10011 $
1#
#1480
0#
#1485
b10101 *
b10100 $
1#
#1490
0#
#1495
b10110 *
b10101 $
1#
#1500
0#
#1505
b10111 *
b10110 $
1#
#1510
0#
#1515
b11000 *
b10111 $
1#
#1520
0#
#1525
b11001 *
b11000 $
1#
#1530
0#
#1535
b11010 *
b11001 $
1#
#1540
0#
#1545
b11011 *
b11010 $
1#
#1550
0#
#1555
b11100 *
b11011 $
1#
#1560
0#
#1565
b11101 *
b11100 $
1#
#1570
0#
#1575
b10 !
b10 (
b111 +
b0 *
b11101 $
1#
#1580
0#
#1585
b1 *
b1100 '
b111 &
b0 $
1#
#1590
0#
#1595
b10 *
b1 $
1#
#1600
0#
#1605
b11 *
b10 $
1#
#1610
0#
#1615
b100 *
b11 $
1#
#1620
0#
#1625
b1 !
b1 (
b1000 +
b0 *
b100 $
1#
#1630
0#
#1635
b1 *
b1101 '
b1000 &
b0 $
1#
#1640
0#
#1645
b10 *
b1 $
1#
#1650
0#
#1655
b11 *
b10 $
1#
#1660
0#
#1665
b100 *
b11 $
1#
#1670
0#
#1675
b101 *
b100 $
1#
#1680
0#
#1685
b110 *
b101 $
1#
#1690
0#
#1695
b111 *
b110 $
1#
#1700
0#
#1705
b1000 *
b111 $
1#
#1710
0#
#1715
b1001 *
b1000 $
1#
#1720
0#
#1725
b1010 *
b1001 $
1#
#1730
0#
#1735
b1011 *
b1010 $
1#
#1740
0#
#1745
b1100 *
b1011 $
1#
#1750
0#
#1755
b1101 *
b1100 $
1#
#1760
0#
#1765
b1110 *
b1101 $
1#
#1770
0#
#1775
b10 !
b10 (
b1001 +
b0 *
b1110 $
1#
#1780
0#
#1785
b1 *
b1110 '
b1001 &
b0 $
1#
#1790
0#
#1795
b10 *
b1 $
1#
#1800
0#
#1805
b11 *
b10 $
1#
#1810
0#
#1815
b100 *
b11 $
1#
#1820
0#
#1825
b1000 !
b1000 (
b1010 +
b0 *
b100 $
1#
#1830
0#
#1835
b1 *
b1111 '
b1010 &
b0 $
1#
#1840
0#
#1845
b10 *
b1 $
1#
#1850
0#
#1855
b100 "
b100 )
b1 +
b0 *
b10 $
1#
#1860
0#
#1865
b1 *
b10000 '
b1 &
b0 $
1#
#1870
0#
#1875
b10 *
b1 $
1#
#1880
0#
#1885
b11 *
b10 $
1#
#1890
0#
#1895
b100 *
b11 $
1#
#1900
0#
#1905
b101 *
b100 $
1#
#1910
0#
#1915
b110 *
b101 $
1#
#1920
0#
#1925
b111 *
b110 $
1#
#1930
0#
#1935
b1000 *
b111 $
1#
#1940
0#
#1945
b1001 *
b1000 $
1#
#1950
0#
#1955
b1010 *
b1001 $
1#
#1960
0#
#1965
b1011 *
b1010 $
1#
#1970
0#
#1975
b1100 *
b1011 $
1#
#1980
0#
#1985
b1101 *
b1100 $
1#
#1990
0#
#1995
b1110 *
b1101 $
1#
#2000
0#
#2005
b1111 *
b1110 $
1#
#2010
0#
#2015
b10000 *
b1111 $
1#
#2020
0#
#2025
b10001 *
b10000 $
1#
#2030
0#
#2035
b10010 *
b10001 $
1#
#2040
0#
#2045
b10011 *
b10010 $
1#
#2050
0#
#2055
b10100 *
b10011 $
1#
#2060
0#
#2065
b10101 *
b10100 $
1#
#2070
0#
#2075
b10110 *
b10101 $
1#
#2080
0#
#2085
b10111 *
b10110 $
1#
#2090
0#
#2095
b11000 *
b10111 $
1#
#2100
0#
#2105
b11001 *
b11000 $
1#
#2110
0#
#2115
b11010 *
b11001 $
1#
#2120
0#
#2125
b11011 *
b11010 $
1#
#2130
0#
#2135
b11100 *
b11011 $
1#
#2140
0#
#2145
b11101 *
b11100 $
1#
#2150
0#
#2155
b11110 *
b11101 $
1#
#2160
0#
#2165
b11111 *
b11110 $
1#
#2170
0#
#2175
b100000 *
b11111 $
1#
#2180
0#
#2185
b100001 *
b100000 $
1#
#2190
0#
#2195
b100010 *
b100001 $
1#
#2200
0#
#2205
b100011 *
b100010 $
1#
#2210
0#
#2215
b100100 *
b100011 $
1#
#2220
0#
#2225
b100101 *
b100100 $
1#
#2230
0#
#2235
b100110 *
b100101 $
1#
#2240
0#
#2245
b100111 *
b100110 $
1#
#2250
0#
#2255
b10 "
b10 )
b10 +
b0 *
b100111 $
1#
#2260
0#
#2265
b1 *
b10001 '
b10 &
b0 $
1#
#2270
0#
#2275
b10 *
b1 $
1#
#2280
0#
#2285
b11 *
b10 $
1#
#2290
0#
#2295
b100 *
b11 $
1#
#2300
0#
#2305
b1 "
b1 )
b11 +
b0 *
b100 $
1#
#2310
0#
#2315
b1 *
b10010 '
b11 &
b0 $
1#
#2320
0#
#2325
b10 *
b1 $
1#
#2330
0#
#2335
b11 *
b10 $
1#
#2340
0#
#2345
b100 *
b11 $
1#
#2350
0#
#2355
b101 *
b100 $
1#
#2360
0#
#2365
b110 *
b101 $
1#
#2370
0#
#2375
b111 *
b110 $
1#
#2380
0#
#2385
b1000 *
b111 $
1#
#2390
0#
#2395
b1001 *
b1000 $
1#
#2400
0#
#2405
b1010 *
b1001 $
1#
#2410
0#
#2415
b1011 *
b1010 $
1#
#2420
0#
#2425
b1100 *
b1011 $
1#
#2430
0#
#2435
b1101 *
b1100 $
1#
#2440
0#
#2445
b1110 *
b1101 $
1#
#2450
0#
#2455
b10 "
b10 )
b100 +
b0 *
b1110 $
1#
#2460
0#
#2465
b1 *
b10011 '
b100 &
b0 $
1#
#2470
0#
#2475
b10 *
b1 $
1#
#2480
0#
#2485
b11 *
b10 $
1#
#2490
0#
#2495
b100 *
b11 $
1#
#2500
0#
#2505
b1000 "
b1000 )
b101 +
b0 *
b100 $
1#
#2510
0#
#2515
b1 *
b10100 '
b101 &
b0 $
1#
#2520
0#
#2525
b100 !
b100 (
b110 +
b0 *
1#
#2530
0#
#2535
b1 *
1#
