homework/homework09/light/light.v
module traffic_light(clk, reset, light_ew_rgyl, light_sn_rgyl); 

input clk;
input reset;
output [3:0] light_ew_rgyl;
output [3:0] light_sn_rgyl;

`define idle 0
`define pre 11 
`define ew_green 1
`define ew_yellow 2
`define ew_left 3
`define ew_yellow_next 4
`define ew_red 5
`define sn_green 6
`define sn_yellow 7
`define sn_left 8
`define sn_yellow_next 9
`define sn_red 10

reg [3:0] status;

assign light_ew_rgyl[0] = (status == `ew_left);
assign light_ew_rgyl[1] = (status == `ew_yellow || status == `ew_yellow_next);
assign light_ew_rgyl[2] = (status == `ew_green);
assign light_ew_rgyl[3] = (status != `ew_green) && (status != `ew_yellow) && (status != `ew_yellow_next) && (status != `ew_left);
assign light_sn_rgyl[0] = (status == `sn_left);
assign light_sn_rgyl[1] = (status == `sn_yellow || status == `sn_yellow_next);
assign light_sn_rgyl[2] = (status == `sn_green);
assign light_sn_rgyl[3] = (status != `sn_green) && (status != `sn_yellow) && (status != `sn_yellow_next) && (status != `sn_left);

always @(posedge clk or reset) begin
    if (reset) begin
        status <= `idle;
    end
    else begin
        case (status)
            `idle: wait_and_change(3, `sn_green, status);
            `sn_green: wait_and_change(30, `sn_yellow, status);
            `sn_yellow: wait_and_change(5, `sn_left, status);
            `sn_left: wait_and_change(15, `sn_yellow_next, status);
            `sn_yellow_next: wait_and_change(5, `sn_red, status);
            `sn_red: wait_and_change(3, `ew_green, status);
            `ew_green: wait_and_change(40, `ew_yellow, status);
            `ew_yellow: wait_and_change(5, `ew_left, status);
            `ew_left: wait_and_change(15, `ew_yellow_next, status);
            `ew_yellow_next: wait_and_change(5, `ew_red, status);
            `ew_red: wait_and_change(2, `sn_green, status);
            default: status <= `idle;
        endcase
    end
end

task automatic wait_and_change; 
    input [7:0] tiks;
    input [3:0] next;
    output [3:0] next_status;
    begin
        repeat (tiks - 1) @ (posedge clk);
        next_status = next;
    end
endtask


endmodule

homework/homework09/light/light_tb.v
`include "light.v"

module test (

);

reg clk, reset;
wire  [3:0] light_ew_rgyl;
wire [3:0] light_sn_rgyl;

traffic_light u(
    clk, reset, light_ew_rgyl, light_sn_rgyl
);

always #1 clk = ~clk;

integer i;
reg [3:0] sta;
reg [7:0] cnt;

initial begin
    $dumpfile("test.vcd");
    $dumpvars;
    clk = 0;
    #1 reset = 1;
    #1 reset = 0;
    sta = u.status;
    cnt = 0;
    for (i = 0; i < 20; i = i) begin
        @(posedge clk) begin
            cnt = cnt + 1; 
        end
        if (u.status != sta) begin
            $display("state: %d, last: %d", sta, cnt); 
            sta = u.status;
            cnt = 0;
            i = i + 1;
        end
    end    
    #20;
    $finish;
end

endmodule

homework/homework09/light/test.vcd
$date
	Thu Nov  5 20:11:50 2020
$end
$version
	Icarus Verilog
$end
$timescale
	1s
$end
$scope module test $end
$var wire 4 ! light_sn_rgyl [3:0] $end
$var wire 4 " light_ew_rgyl [3:0] $end
$var reg 1 # clk $end
$var reg 8 $ cnt [7:0] $end
$var reg 1 % reset $end
$var reg 4 & sta [3:0] $end
$var integer 32 ' i [31:0] $end
$scope module u $end
$var wire 1 # clk $end
$var wire 1 % reset $end
$var wire 4 ( light_sn_rgyl [3:0] $end
$var wire 4 ) light_ew_rgyl [3:0] $end
$var reg 4 * status [3:0] $end
$scope task wait_and_change $end
$upscope $end
$upscope $end
$upscope $end
$enddefinitions $end
#0
$dumpvars
bx *
bx )
bx (
bx '
bx &
x%
bx $
0#
bx "
bx !
$end
#1
b0 "
b0 )
b0 !
b0 (
b0 *
1%
1#
#2
b0 '
b0 $
b0 &
0%
0#
#3
b1 $
1#
#4
0#
#5
b1000 "
b1000 )
b100 !
b100 (
b110 *
b10 $
1#
#6
0#
#7
b1 '
b110 &
b0 $
1#
#8
0#
#9
b1 $
1#
#10
0#
#11
b10 $
1#
#12
0#
#13
b11 $
1#
#14
0#
#15
b100 $
1#
#16
0#
#17
b101 $
1#
#18
0#
#19
b110 $
1#
#20
0#
#21
b111 $
1#
#22
0#
#23
b1000 $
1#
#24
0#
#25
b1001 $
1#
#26
0#
#27
b1010 $
1#
#28
0#
#29
b1011 $
1#
#30
0#
#31
b1100 $
1#
#32
0#
#33
b1101 $
1#
#34
0#
#35
b1110 $
1#
#36
0#
#37
b1111 $
1#
#38
0#
#39
b10000 $
1#
#40
0#
#41
b10001 $
1#
#42
0#
#43
b10010 $
1#
#44
0#
#45
b10011 $
1#
#46
0#
#47
b10100 $
1#
#48
0#
#49
b10101 $
1#
#50
0#
#51
b10110 $
1#
#52
0#
#53
b10111 $
1#
#54
0#
#55
b11000 $
1#
#56
0#
#57
b11001 $
1#
#58
0#
#59
b11010 $
1#
#60
0#
#61
b11011 $
1#
#62
0#
#63
b11100 $
1#
#64
0#
#65
b10 !
b10 (
b111 *
b11101 $
1#
#66
0#
#67
b10 '
b111 &
b0 $
1#
#68
0#
#69
b1 $
1#
#70
0#
#71
b10 $
1#
#72
0#
#73
b11 $
1#
#74
0#
#75
b1000 "
b1000 )
b1 !
b1 (
b1000 *
b100 $
1#
#76
0#
#77
b11 '
b1000 &
b0 $
1#
#78
0#
#79
b1 $
1#
#80
0#
#81
b10 $
1#
#82
0#
#83
b11 $
1#
#84
0#
#85
b100 $
1#
#86
0#
#87
b101 $
1#
#88
0#
#89
b110 $
1#
#90
0#
#91
b111 $
1#
#92
0#
#93
b1000 $
1#
#94
0#
#95
b1001 $
1#
#96
0#
#97
b1010 $
1#
#98
0#
#99
b1011 $
1#
#100
0#
#101
b1100 $
1#
#102
0#
#103
b1101 $
1#
#104
0#
#105
b10 !
b10 (
b1001 *
b1110 $
1#
#106
0#
#107
b100 '
b1001 &
b0 $
1#
#108
0#
#109
b1 $
1#
#110
0#
#111
b10 $
1#
#112
0#
#113
b11 $
1#
#114
0#
#115
b1000 !
b1000 (
b1010 *
b100 $
1#
#116
0#
#117
b101 '
b1010 &
b0 $
1#
#118
0#
#119
b1 $
1#
#120
0#
#121
b100 "
b100 )
b1 *
b10 $
1#
#122
0#
#123
b110 '
b1 &
b0 $
1#
#124
0#
#125
b1 $
1#
#126
0#
#127
b10 $
1#
#128
0#
#129
b11 $
1#
#130
0#
#131
b100 $
1#
#132
0#
#133
b101 $
1#
#134
0#
#135
b110 $
1#
#136
0#
#137
b111 $
1#
#138
0#
#139
b1000 $
1#
#140
0#
#141
b1001 $
1#
#142
0#
#143
b1010 $
1#
#144
0#
#145
b1011 $
1#
#146
0#
#147
b1100 $
1#
#148
0#
#149
b1101 $
1#
#150
0#
#151
b1110 $
1#
#152
0#
#153
b1111 $
1#
#154
0#
#155
b10000 $
1#
#156
0#
#157
b10001 $
1#
#158
0#
#159
b10010 $
1#
#160
0#
#161
b10011 $
1#
#162
0#
#163
b10100 $
1#
#164
0#
#165
b10101 $
1#
#166
0#
#167
b10110 $
1#
#168
0#
#169
b10111 $
1#
#170
0#
#171
b11000 $
1#
#172
0#
#173
b11001 $
1#
#174
0#
#175
b11010 $
1#
#176
0#
#177
b11011 $
1#
#178
0#
#179
b11100 $
1#
#180
0#
#181
b11101 $
1#
#182
0#
#183
b11110 $
1#
#184
0#
#185
b11111 $
1#
#186
0#
#187
b100000 $
1#
#188
0#
#189
b100001 $
1#
#190
0#
#191
b100010 $
1#
#192
0#
#193
b100011 $
1#
#194
0#
#195
b100100 $
1#
#196
0#
#197
b100101 $
1#
#198
0#
#199
b100110 $
1#
#200
0#
#201
b10 "
b10 )
b10 *
b100111 $
1#
#202
0#
#203
b111 '
b10 &
b0 $
1#
#204
0#
#205
b1 $
1#
#206
0#
#207
b10 $
1#
#208
0#
#209
b11 $
1#
#210
0#
#211
b1000 !
b1000 (
b1 "
b1 )
b11 *
b100 $
1#
#212
0#
#213
b1000 '
b11 &
b0 $
1#
#214
0#
#215
b1 $
1#
#216
0#
#217
b10 $
1#
#218
0#
#219
b11 $
1#
#220
0#
#221
b100 $
1#
#222
0#
#223
b101 $
1#
#224
0#
#225
b110 $
1#
#226
0#
#227
b111 $
1#
#228
0#
#229
b1000 $
1#
#230
0#
#231
b1001 $
1#
#232
0#
#233
b1010 $
1#
#234
0#
#235
b1011 $
1#
#236
0#
#237
b1100 $
1#
#238
0#
#239
b1101 $
1#
#240
0#
#241
b10 "
b10 )
b100 *
b1110 $
1#
#242
0#
#243
b1001 '
b100 &
b0 $
1#
#244
0#
#245
b1 $
1#
#246
0#
#247
b10 $
1#
#248
0#
#249
b11 $
1#
#250
0#
#251
b1000 "
b1000 )
b101 *
b100 $
1#
#252
0#
#253
b1010 '
b101 &
b0 $
1#
#254
0#
#255
b100 !
b100 (
b110 *
b1 $
1#
#256
0#
#257
b1011 '
b110 &
b0 $
1#
#258
0#
#259
b1 $
1#
#260
0#
#261
b10 $
1#
#262
0#
#263
b11 $
1#
#264
0#
#265
b100 $
1#
#266
0#
#267
b101 $
1#
#268
0#
#269
b110 $
1#
#270
0#
#271
b111 $
1#
#272
0#
#273
b1000 $
1#
#274
0#
#275
b1001 $
1#
#276
0#
#277
b1010 $
1#
#278
0#
#279
b1011 $
1#
#280
0#
#281
b1100 $
1#
#282
0#
#283
b1101 $
1#
#284
0#
#285
b1110 $
1#
#286
0#
#287
b1111 $
1#
#288
0#
#289
b10000 $
1#
#290
0#
#291
b10001 $
1#
#292
0#
#293
b10010 $
1#
#294
0#
#295
b10011 $
1#
#296
0#
#297
b10100 $
1#
#298
0#
#299
b10101 $
1#
#300
0#
#301
b10110 $
1#
#302
0#
#303
b10111 $
1#
#304
0#
#305
b11000 $
1#
#306
0#
#307
b11001 $
1#
#308
0#
#309
b11010 $
1#
#310
0#
#311
b11011 $
1#
#312
0#
#313
b11100 $
1#
#314
0#
#315
b10 !
b10 (
b111 *
b11101 $
1#
#316
0#
#317
b1100 '
b111 &
b0 $
1#
#318
0#
#319
b1 $
1#
#320
0#
#321
b10 $
1#
#322
0#
#323
b11 $
1#
#324
0#
#325
b1000 "
b1000 )
b1 !
b1 (
b1000 *
b100 $
1#
#326
0#
#327
b1101 '
b1000 &
b0 $
1#
#328
0#
#329
b1 $
1#
#330
0#
#331
b10 $
1#
#332
0#
#333
b11 $
1#
#334
0#
#335
b100 $
1#
#336
0#
#337
b101 $
1#
#338
0#
#339
b110 $
1#
#340
0#
#341
b111 $
1#
#342
0#
#343
b1000 $
1#
#344
0#
#345
b1001 $
1#
#346
0#
#347
b1010 $
1#
#348
0#
#349
b1011 $
1#
#350
0#
#351
b1100 $
1#
#352
0#
#353
b1101 $
1#
#354
0#
#355
b10 !
b10 (
b1001 *
b1110 $
1#
#356
0#
#357
b1110 '
b1001 &
b0 $
1#
#358
0#
#359
b1 $
1#
#360
0#
#361
b10 $
1#
#362
0#
#363
b11 $
1#
#364
0#
#365
b1000 !
b1000 (
b1010 *
b100 $
1#
#366
0#
#367
b1111 '
b1010 &
b0 $
1#
#368
0#
#369
b1 $
1#
#370
0#
#371
b100 "
b100 )
b1 *
b10 $
1#
#372
0#
#373
b10000 '
b1 &
b0 $
1#
#374
0#
#375
b1 $
1#
#376
0#
#377
b10 $
1#
#378
0#
#379
b11 $
1#
#380
0#
#381
b100 $
1#
#382
0#
#383
b101 $
1#
#384
0#
#385
b110 $
1#
#386
0#
#387
b111 $
1#
#388
0#
#389
b1000 $
1#
#390
0#
#391
b1001 $
1#
#392
0#
#393
b1010 $
1#
#394
0#
#395
b1011 $
1#
#396
0#
#397
b1100 $
1#
#398
0#
#399
b1101 $
1#
#400
0#
#401
b1110 $
1#
#402
0#
#403
b1111 $
1#
#404
0#
#405
b10000 $
1#
#406
0#
#407
b10001 $
1#
#408
0#
#409
b10010 $
1#
#410
0#
#411
b10011 $
1#
#412
0#
#413
b10100 $
1#
#414
0#
#415
b10101 $
1#
#416
0#
#417
b10110 $
1#
#418
0#
#419
b10111 $
1#
#420
0#
#421
b11000 $
1#
#422
0#
#423
b11001 $
1#
#424
0#
#425
b11010 $
1#
#426
0#
#427
b11011 $
1#
#428
0#
#429
b11100 $
1#
#430
0#
#431
b11101 $
1#
#432
0#
#433
b11110 $
1#
#434
0#
#435
b11111 $
1#
#436
0#
#437
b100000 $
1#
#438
0#
#439
b100001 $
1#
#440
0#
#441
b100010 $
1#
#442
0#
#443
b100011 $
1#
#444
0#
#445
b100100 $
1#
#446
0#
#447
b100101 $
1#
#448
0#
#449
b100110 $
1#
#450
0#
#451
b10 "
b10 )
b10 *
b100111 $
1#
#452
0#
#453
b10001 '
b10 &
b0 $
1#
#454
0#
#455
b1 $
1#
#456
0#
#457
b10 $
1#
#458
0#
#459
b11 $
1#
#460
0#
#461
b1000 !
b1000 (
b1 "
b1 )
b11 *
b100 $
1#
#462
0#
#463
b10010 '
b11 &
b0 $
1#
#464
0#
#465
b1 $
1#
#466
0#
#467
b10 $
1#
#468
0#
#469
b11 $
1#
#470
0#
#471
b100 $
1#
#472
0#
#473
b101 $
1#
#474
0#
#475
b110 $
1#
#476
0#
#477
b111 $
1#
#478
0#
#479
b1000 $
1#
#480
0#
#481
b1001 $
1#
#482
0#
#483
b1010 $
1#
#484
0#
#485
b1011 $
1#
#486
0#
#487
b1100 $
1#
#488
0#
#489
b1101 $
1#
#490
0#
#491
b10 "
b10 )
b100 *
b1110 $
1#
#492
0#
#493
b10011 '
b100 &
b0 $
1#
#494
0#
#495
b1 $
1#
#496
0#
#497
b10 $
1#
#498
0#
#499
b11 $
1#
#500
0#
#501
b1000 "
b1000 )
b101 *
b100 $
1#
#502
0#
#503
b10100 '
b101 &
b0 $
1#
#504
0#
#505
b100 !
b100 (
b110 *
1#
