homework/homework07/mux4/mux.v
module mux4 (
    en,
    s,
    d,
    y
);

input en;
input [1:0] s;
input [3:0] d;
output y;

assign y = en ? d[s] : 0;
    
endmodule

homework/homework07/mux4/test_mux.v
`include "mux.v"

module test (

);

reg en;
reg [1:0] s;
reg [3:0] d;
wire y;

mux4 u_mux(
    .en(en),
    .s(s),
    .d(d),
    .y(y)
);

reg en_r [99:0];
reg [1:0] s_r [99:0];
reg [3:0] d_r [99:0];
reg y_r [99:0];

integer i;

initial begin
    $dumpfile("test.vcd");
    $dumpvars;
    $readmemb("en.ram", en_r);
    $readmemb("s.ram", s_r);
    $readmemb("d.ram", d_r);
    $readmemb("y.ram", y_r);
    for (i = 0; i < 100; i = i + 1) begin
        en = en_r[i];
        s = s_r[i];
        d = d_r[i];
        #1;
        if (y != y_r[i]) begin
            $display("failed, y:%x y_r:%x", y, y_r[i]);
            $finish;
        end
    end
    $display("passed");
    $finish;
end
    
endmodule

homework/homework07/mux4/test.vcd
$date
	Mon Oct 19 18:48:41 2020
$end
$version
	Icarus Verilog
$end
$timescale
	1s
$end
$scope module test $end
$var wire 1 ! y $end
$var reg 4 " d [3:0] $end
$var reg 1 # en $end
$var reg 2 $ s [1:0] $end
$var integer 32 % i [31:0] $end
$scope module u_mux $end
$var wire 4 & d [3:0] $end
$var wire 1 # en $end
$var wire 2 ' s [1:0] $end
$var wire 1 ! y $end
$upscope $end
$upscope $end
$enddefinitions $end
#0
$dumpvars
b11 '
b1111 &
b0 %
b11 $
1#
b1111 "
1!
$end
#1
0!
b1010 "
b1010 &
b0 $
b0 '
0#
b1 %
#2
b1000 "
b1000 &
b10 %
#3
b111 "
b111 &
b11 %
#4
b1010 "
b1010 &
b10 $
b10 '
b100 %
#5
b1001 "
b1001 &
b1 $
b1 '
b101 %
#6
b1010 "
b1010 &
b11 $
b11 '
b110 %
#7
1!
b1111 "
b1111 &
b0 $
b0 '
1#
b111 %
#8
b1100 "
b1100 &
b11 $
b11 '
b1000 %
#9
0!
b10 "
b10 &
b0 $
b0 '
b1001 %
#10
1!
b110 "
b110 &
b10 $
b10 '
b1010 %
#11
0!
b1 "
b1 &
b11 $
b11 '
b1011 %
#12
1!
b1100 "
b1100 &
b10 $
b10 '
b1100 %
#13
0!
b1000 "
b1000 &
b0 $
b0 '
0#
b1101 %
#14
b11 "
b11 &
b10 $
b10 '
1#
b1110 %
#15
1!
b1100 "
b1100 &
b1111 %
#16
0!
b111 "
b111 &
b11 $
b11 '
b10000 %
#17
b1000 "
b1000 &
b1 $
b1 '
b10001 %
#18
b1101 "
b1101 &
b0 $
b0 '
0#
b10010 %
#19
b1010 "
b1010 &
1#
b10011 %
#20
1!
b1000 "
b1000 &
b11 $
b11 '
b10100 %
#21
0!
b0 "
b0 &
0#
b10101 %
#22
1!
b1111 "
b1111 &
b0 $
b0 '
1#
b10110 %
#23
0!
b1011 "
b1011 &
b11 $
b11 '
0#
b10111 %
#24
b100 "
b100 &
b0 $
b0 '
1#
b11000 %
#25
b1001 "
b1001 &
0#
b11001 %
#26
b11 "
b11 &
b11010 %
#27
b1011 "
b1011 &
b11 $
b11 '
b11011 %
#28
b1111 "
b1111 &
b11100 %
#29
b0 "
b0 &
b10 $
b10 '
1#
b11101 %
#30
b1010 "
b1010 &
b0 $
b0 '
b11110 %
#31
b110 "
b110 &
b1 $
b1 '
0#
b11111 %
#32
b101 "
b101 &
b11 $
b11 '
b100000 %
#33
b1001 "
b1001 &
b100001 %
#34
b1100 "
b1100 &
b0 $
b0 '
b100010 %
#35
b111 "
b111 &
b1 $
b1 '
b100011 %
#36
1!
b1111 "
b1111 &
1#
b100100 %
#37
b110 "
b110 &
b10 $
b10 '
b100101 %
#38
0!
b100 "
b100 &
b1 $
b1 '
b100110 %
#39
b11 $
b11 '
b100111 %
#40
b1010 "
b1010 &
0#
b101000 %
#41
b0 "
b0 &
b1 $
b1 '
1#
b101001 %
#42
0#
b101010 %
#43
b1 "
b1 &
b101011 %
#44
b0 $
b0 '
b101100 %
#45
b100 "
b100 &
b11 $
b11 '
b101101 %
#46
b1001 "
b1001 &
b10 $
b10 '
1#
b101110 %
#47
b1010 "
b1010 &
b101111 %
#48
1!
b1110 "
b1110 &
b110000 %
#49
0!
b1 "
b1 &
0#
b110001 %
#50
b1101 "
b1101 &
b11 $
b11 '
b110010 %
#51
b1000 "
b1000 &
b1 $
b1 '
b110011 %
#52
1!
b110 "
b110 &
1#
b110100 %
#53
b111 "
b111 &
b10 $
b10 '
b110101 %
#54
0!
b1111 "
b1111 &
b0 $
b0 '
0#
b110110 %
#55
b1110 "
b1110 &
b10 $
b10 '
b110111 %
#56
1!
b1111 "
b1111 &
b0 $
b0 '
1#
b111000 %
#57
b111 "
b111 &
b10 $
b10 '
b111001 %
#58
0!
b1000 "
b1000 &
b0 $
b0 '
0#
b111010 %
#59
b101 "
b101 &
b11 $
b11 '
1#
b111011 %
#60
b1111 "
b1111 &
b0 $
b0 '
0#
b111100 %
#61
b1 "
b1 &
b11 $
b11 '
1#
b111101 %
#62
1!
b1011 "
b1011 &
b111110 %
#63
0!
b101 "
b101 &
b111111 %
#64
b11 "
b11 &
b1000000 %
#65
1!
b10 "
b10 &
b1 $
b1 '
b1000001 %
#66
0!
b1101 "
b1101 &
0#
b1000010 %
#67
1!
b110 "
b110 &
1#
b1000011 %
#68
b1111 "
b1111 &
b10 $
b10 '
b1000100 %
#69
0!
b1001 "
b1001 &
b0 $
b0 '
0#
b1000101 %
#70
b10 $
b10 '
b1000110 %
#71
b1101 "
b1101 &
b11 $
b11 '
b1000111 %
#72
1!
b1011 "
b1011 &
b1 $
b1 '
1#
b1001000 %
#73
0!
b111 "
b111 &
b11 $
b11 '
b1001001 %
#74
1!
b1000 "
b1000 &
b1001010 %
#75
0!
b10 "
b10 &
b10 $
b10 '
b1001011 %
#76
b1101 "
b1101 &
b1 $
b1 '
b1001100 %
#77
1!
b1010 "
b1010 &
b1001101 %
#78
0!
b1111 "
b1111 &
b11 $
b11 '
0#
b1001110 %
#79
b100 "
b100 &
b0 $
b0 '
b1001111 %
#80
1!
b11 "
b11 &
b1 $
b1 '
1#
b1010000 %
#81
b1010001 %
#82
0!
b100 "
b100 &
0#
b1010010 %
#83
b1101 "
b1101 &
b10 $
b10 '
b1010011 %
#84
b1011 "
b1011 &
1#
b1010100 %
#85
b10 "
b10 &
b0 $
b0 '
0#
b1010101 %
#86
1!
b1110 "
b1110 &
b1 $
b1 '
1#
b1010110 %
#87
0!
b11 "
b11 &
0#
b1010111 %
#88
1!
b1001 "
b1001 &
b11 $
b11 '
1#
b1011000 %
#89
b1000 "
b1000 &
b1011001 %
#90
b1 "
b1 &
b0 $
b0 '
b1011010 %
#91
0!
b1110 "
b1110 &
b10 $
b10 '
0#
b1011011 %
#92
b1 $
b1 '
b1011100 %
#93
1!
b101 "
b101 &
b0 $
b0 '
1#
b1011101 %
#94
0!
b10 "
b10 &
b10 $
b10 '
0#
b1011110 %
#95
b0 "
b0 &
1#
b1011111 %
#96
b110 "
b110 &
b0 $
b0 '
0#
b1100000 %
#97
1!
b1110 "
b1110 &
b1 $
b1 '
1#
b1100001 %
#98
0!
b110 "
b110 &
b0 $
b0 '
b1100010 %
#99
b1010 "
b1010 &
0#
b1100011 %
#100
b1100100 %
